Workbook

Sheet Screening
A1: Title | B1: Link | C1: Source | D1: Abstract | E1: Irrelevant title/abstract | F1: Dataset (if not DAIC-WOZ) | G1: Does not regard DAIC-WOZ | H1: Does not use MAE | I1: Does not introduce new model | J1: Not in English | K1: Not retrieved | L1: Discarded after full-text review | M1: Data preprocessing | N1: Data partitioning | O1: Partitions disjoint level | P1: Model description | Q1: Training details | R1: Final model selection | S1: - | T1: Data modality | U1: Dev. MAE | V1: Dev. RMSE | W1: Dev. R2 | X1: Test. MAE | Y1: Test. RMSE | Z1: Test. R2 | AA1: Code available | AB1: Repeated experiments | AC1: Uses interviewer's prompts | AD1: Participant inter-partition leakage | AE1: -- | AF1: Included | AG1: Comment
A2: Hierarchical Attention Transfer Networks for Depression Assessment from Speech | B2: https://doi.org/10.1109/ICASSP40776.2020.9053207 | C2: Scopus | D2: A growing area of mental health research is the search for speech-based objective markers for conditions such as depression. However, when combined with machine learning, this search can be challenging due to a limited amount of annotated training data. In this paper, we propose a novel crosstask approach which transfers attention mechanisms from speech recognition to aid depression severity measurement. This transfer is applied in a two-level hierarchical network which mirrors the natural hierarchical structure of speech. Experiments based on the Distress Analysis Interview Corpus-Wizard of Oz (DAIC-WOZ) dataset, as used in the 2017 Audio/Visual Emotion Challenge, demonstrate the effectiveness of our Hierarchical Attention Transfer Network. On the development set, the proposed approach achieves a root mean square error (RMSE) of 3.85, and a mean absolute error (MAE) of 2.99, on a Patient Health Questionnaire (PHQ)-8 scale [0], [24], while on the test set, it achieves an RMSE of 5.66 and an MAE of 4.28. To the best of our knowledge, these scores represent the best-known speech-only results to date on this corpus. © 2020 IEEE. | E2: FALSE | L2: =IF(OR(Table1[[#This Row],[Does not regard DAIC-WOZ]]=TRUE,Table1[[#This Row],[Does not use MAE]]=TRUE,Table1[[#This Row],[Does not introduce new model]]=TRUE,Table1[[#This Row],[Not in English]]=TRUE,Table1[[#This Row],[Not retrieved]]=TRUE),TRUE,FALSE) -> FALSE | M2: MEL Spectrogram | N2: - | O2: Participant turn | P2: Attention transfer BLSTM | Q2: - | R2: - | T2: A | U2: 2.99 | V2: 3.85 | W2: - | X2: 4.28 | Y2: 5.66 | Z2: - | AA2: No | AB2: No | AC2: Yes | AD2: - | AF2: =IF(NOT(Table1[[#This Row],[Data modality]] = ""), NOT(OR(Table1[[#This Row],[Data preprocessing]] = "-", Table1[[#This Row],[Data partitioning]] = "-", Table1[[#This Row],[Partitions disjoint level]] = "-", Table1[[#This Row],[Model description]] ="-", Table1[[#This Row],[Training details]] = "-", Table1[[#This Row],[Final model selection]] = "-", Table1[[#This Row],[Discarded after full-text review]])),"") -> FALSE | AG2: No information about ASR system training. Neither dataset partition utilized nor description of convergence criteria
A3: PointTransform Networks for automatic depression level prediction via facial keypoints | B3: https://doi.org/10.1016/j.knosys.2024.111951 | C3: ScienceDirect | D3: According to physiological reports, individuals with different levels of depression present various facial dynamic patterns. Thus, researchers have examined facial changes to predict depression severity. However, they often use facial images or videos of the subjects, which increases the risk of privacy leakage. Therefore, we intend to use the mixer layer to process facial keypoint sequences to predict the depression levels. However, the mixer layer cannot guarantee that the output and input sequences have the same temporal properties, which prevents the residual connection from being additive in a physical sense. To this end, we construct a PointTransform Network (PTN). In the constructed model, a Mixer Attention Layer (MAL) and a Token Sequence Aggregation (TSA) module are proposed. The proposed MAL embeds the results of channel-communication and token-communication into the sequence in the form of weights through the attention mechanism, which maintains the temporal order among tokens in the sequence during the calculation process and compensates for the limitations of the mixer layer. The proposed TSA module can integrate the depression level prediction results of all facial keypoints through the attention mechanism. Therefore, the TSA module achieves the unity of decision-level fusion and tensor vectorization. Experiments are conducted on several benchmark databases and the results demonstrate the effectiveness of our method. | E3: FALSE | L3: =IF(OR(Table1[[#This Row],[Does not regard DAIC-WOZ]]=TRUE,Table1[[#This Row],[Does not use MAE]]=TRUE,Table1[[#This Row],[Does not introduce new model]]=TRUE,Table1[[#This Row],[Not in English]]=TRUE,Table1[[#This Row],[Not retrieved]]=TRUE),TRUE,FALSE) -> FALSE | M3: - | N3: - | O3: - | P3: Point Transform Network | Q3: + | R3: - | T3: V | U3: - | V3: - | W3: - | X3: 3.84 | Y3: 5.08 | Z3: - | AA3: No | AB3: No | AC3: - | AD3: - | AF3: =IF(NOT(Table1[[#This Row],[Data modality]] = ""), NOT(OR(Table1[[#This Row],[Data preprocessing]] = "-", Table1[[#This Row],[Data partitioning]] = "-", Table1[[#This Row],[Partitions disjoint level]] = "-", Table1[[#This Row],[Model description]] ="-", Table1[[#This Row],[Training details]] = "-", Table1[[#This Row],[Final model selection]] = "-", Table1[[#This Row],[Discarded after full-text review]])),"") -> FALSE | AG3: DAIC-WOZ is used only as an example and no information regarding training on this dataset is provided
A4: Image processing system for velocity measurements in natural convection flows | B4: https://doi.org/10.1016/0029-5493(91)90270-R | C4: ScienceDirect | D4: An image processing system based on a particle-tracking method has been developed to measure quantitatively at one time the two-dimensional velocity components arising in natural convection flows. The analysis of the image data proceeds automatically, due in part to the video recording system utilized in our method. The image processing system was applied to the natural convection flows in a 1/10 scale basic reactor model. The velocity vectors and the vorticities were obtained under transient and steady states in different experimental cases, enabling us to examine in detail the transition of the flow patterns and other aspects under different experimental conditions. The uncertainty of this system was evaluated for use in our experiments and it was confirmed that the margin of error is acceptable. | E4: TRUE | L4: =IF(OR(Table1[[#This Row],[Does not regard DAIC-WOZ]]=TRUE,Table1[[#This Row],[Does not use MAE]]=TRUE,Table1[[#This Row],[Does not introduce new model]]=TRUE,Table1[[#This Row],[Not in English]]=TRUE,Table1[[#This Row],[Not retrieved]]=TRUE),TRUE,FALSE) -> FALSE | AF4: =IF(NOT(Table1[[#This Row],[Data modality]] = ""), NOT(OR(Table1[[#This Row],[Data preprocessing]] = "-", Table1[[#This Row],[Data partitioning]] = "-", Table1[[#This Row],[Partitions disjoint level]] = "-", Table1[[#This Row],[Model description]] ="-", Table1[[#This Row],[Training details]] = "-", Table1[[#This Row],[Final model selection]] = "-", Table1[[#This Row],[Discarded after full-text review]])),"")
A5: Multilevel depression status detection based on fine-grained prompt learning | B5: https://doi.org/10.1016/j.patrec.2024.01.005 | C5: ScienceDirect | D5: As a common psychological disorder, depression is generally detected based on scales and interviews, which are often affected by subjective or environmental factors. In order to assist in the diagnosis, automatic depression detection (ADD) is developed to provide an objective, efficient, and convenient technique based on the analysis of different psychophysiological data. Among them, text is one of the most frequently used modalities in the research field of ADD. Despite its success, several key issues still need to be addressed. Specifically, binary detection performed in the classical ADD methods cannot satisfy the demand for early detection tasks. Therefore, a more fine-grained analysis of depression status is highly needed. Moreover, due to factors such as small dataset size and improper organization of interview texts by selecting response texts only or choosing topics subjectively, insufficient learnable representations for depression detection are inevitable. To tackle these issues, we propose a multilevel depression status detection approach based on fine-grained prompt learning, called MDSD-FGPL. In our method, we design multiple sets of prompts from coarse-grained to fine-grained and therefore train the language model with features extracted from different depressive levels. We also reorganize the interview text at the question-response level and utilize the attention mechanism to capture and fuse the key features. Specifically, two model branches are constructed based on pre-trained language models for extracting comprehensive semantic features and depression-specific semantic tendencies, respectively. Our method was evaluated on the DAIC-WOZ dataset, showing satisfying performance in fine-grained depression detection. Additionally, our method achieves a state-of-the-art F1-score of 0.8276 in the coarse-grained binary classification. | E5: FALSE | L5: =IF(OR(Table1[[#This Row],[Does not regard DAIC-WOZ]]=TRUE,Table1[[#This Row],[Does not use MAE]]=TRUE,Table1[[#This Row],[Does not introduce new model]]=TRUE,Table1[[#This Row],[Not in English]]=TRUE,Table1[[#This Row],[Not retrieved]]=TRUE),TRUE,FALSE) -> FALSE | M5: Default transcriptions | N5: Default | O5: Participant turn | P5: T5 and BERT embeddings fusion | Q5: - | R5: - | T5: T | U5: - | V5: - | W5: - | X5: 5.28 | Y5: - | Z5: - | AA5: No | AB5: No | AC5: Yes | AD5: No | AF5: =IF(NOT(Table1[[#This Row],[Data modality]] = ""), NOT(OR(Table1[[#This Row],[Data preprocessing]] = "-", Table1[[#This Row],[Data partitioning]] = "-", Table1[[#This Row],[Partitions disjoint level]] = "-", Table1[[#This Row],[Model description]] ="-", Table1[[#This Row],[Training details]] = "-", Table1[[#This Row],[Final model selection]] = "-", Table1[[#This Row],[Discarded after full-text review]])),"") -> FALSE | AG5: No information on model training and selection (hparams, convergence criteria) is provided
A6: A random forest regression method with selected-text feature for depression assessment | B6: https://doi.org/10.1145/3133944.3133951 | C6: Scopus | D6: Audio/visual and mood disorder cues have been recently explored to assist psychologists and psychiatrists in Depression Diagnosis. in this paper, we propose a random forest method with a Selected-Text feature which is according to the analysis on the transcript in different depressive levels. The files are consisted of sleep quality, PTSD/Depression Diagnostic, successive treatment, personal preference and feeling. Experiments are carried out on the Distress Analysis Interview Corpus-Wizard of Oz (DAIC-WOZ) database[6]. Comparing with results obtained with audio based, video based or multi-feature based cascade decision-level fusion features, Selected-Text feature based method has obtained very promising results on the development and test sets. The root mean square error(RMSE) reaches 4.7, and mean absolute error(MAE) reaches 3.9, which are better than the baseline result, i.e. 7.05/5.66. © 2017 Copyright held by the owner/author(s). | E6: FALSE | L6: =IF(OR(Table1[[#This Row],[Does not regard DAIC-WOZ]]=TRUE,Table1[[#This Row],[Does not use MAE]]=TRUE,Table1[[#This Row],[Does not introduce new model]]=TRUE,Table1[[#This Row],[Not in English]]=TRUE,Table1[[#This Row],[Not retrieved]]=TRUE),TRUE,FALSE) -> FALSE | M6: Manual feature assignment | N6: Default | O6: Interview | P6: Cascade Random Forest Regression | Q6: - | R6: N/A | T6: V-A-T | U6: - | V6: - | W6: - | X6: 3.87 | Y6: 4.98 | Z6: - | AA6: No | AB6: No | AC6: Yes | AD6: No | AF6: =IF(NOT(Table1[[#This Row],[Data modality]] = ""), NOT(OR(Table1[[#This Row],[Data preprocessing]] = "-", Table1[[#This Row],[Data partitioning]] = "-", Table1[[#This Row],[Partitions disjoint level]] = "-", Table1[[#This Row],[Model description]] ="-", Table1[[#This Row],[Training details]] = "-", Table1[[#This Row],[Final model selection]] = "-", Table1[[#This Row],[Discarded after full-text review]])),"") -> FALSE | AG6: Detailed model specifications (e.g. number of trees in random forest) are not disclosed. Manually prepared features from text per interview may imply bias. Looks a bit similar to https://doi.org/10.1145/3133944.3133951 which was published year before.
A7: MPDRM: A Multi-Scale Personalized Depression Recognition Model via facial movements | B7: https://doi.org/10.1016/j.neucom.2025.129669 | C7: ScienceDirect | D7: Automatic depression recognition based on facial movements in videos has become a research hotspot. However, existing methods tend to confuse individual inherent facial behavioral habits with characteristics specific to depression, which leads to misjudgments. To address this, we propose a Multi-scale Personalized Depression Recognition Model (MPDRM) that mitigates the negative impact of individual differences, enabling the model to focus on general and robust facial depression cues. The proposed model consists of three main components: the Multi-scale Depression Feature Network (MDFN), the Multi-scale Personality Feature Network (MPFN), and the Relational Attention Recognition Module (RARM). The MDFN extracts depression-related information, while the contrastive learning-based MPFN extracts stable personalized information. In both MDFN and MPFN, we insert the Multi-scale Motion Pattern Extraction Module (MMP) to capture rich multi-scale spatiotemporal facial features. Finally, the RARM is designed to enhance the representation of depression and output the results. Cross-validation on a specifically constructed longitudinal dataset demonstrates that our model outperforms other models. Experimental results indicate that suppressing personalized information of facial movements can effectively improve the accuracy of depression recognition. | E7: FALSE | F7: custom | G7: TRUE | L7: =IF(OR(Table1[[#This Row],[Does not regard DAIC-WOZ]]=TRUE,Table1[[#This Row],[Does not use MAE]]=TRUE,Table1[[#This Row],[Does not introduce new model]]=TRUE,Table1[[#This Row],[Not in English]]=TRUE,Table1[[#This Row],[Not retrieved]]=TRUE),TRUE,FALSE) -> TRUE | AF7: =IF(NOT(Table1[[#This Row],[Data modality]] = ""), NOT(OR(Table1[[#This Row],[Data preprocessing]] = "-", Table1[[#This Row],[Data partitioning]] = "-", Table1[[#This Row],[Partitions disjoint level]] = "-", Table1[[#This Row],[Model description]] ="-", Table1[[#This Row],[Training details]] = "-", Table1[[#This Row],[Final model selection]] = "-", Table1[[#This Row],[Discarded after full-text review]])),"")
A8: Conversational assessment using artificial intelligence is as clinically useful as depression scales and preferred by users | B8: https://doi.org/10.1016/j.jad.2024.01.212 | C8: ScienceDirect | D8: Background | E8: TRUE | L8: =IF(OR(Table1[[#This Row],[Does not regard DAIC-WOZ]]=TRUE,Table1[[#This Row],[Does not use MAE]]=TRUE,Table1[[#This Row],[Does not introduce new model]]=TRUE,Table1[[#This Row],[Not in English]]=TRUE,Table1[[#This Row],[Not retrieved]]=TRUE),TRUE,FALSE) -> FALSE | AF8: =IF(NOT(Table1[[#This Row],[Data modality]] = ""), NOT(OR(Table1[[#This Row],[Data preprocessing]] = "-", Table1[[#This Row],[Data partitioning]] = "-", Table1[[#This Row],[Partitions disjoint level]] = "-", Table1[[#This Row],[Model description]] ="-", Table1[[#This Row],[Training details]] = "-", Table1[[#This Row],[Final model selection]] = "-", Table1[[#This Row],[Discarded after full-text review]])),"")
A9: An automatic diagnostic network using skew-robust adversarial discriminative domain adaptation to evaluate the severity of depression | B9: https://doi.org/10.1016/j.cmpb.2019.01.006 | C9: ScienceDirect | D9: Background and Objective | E9: FALSE | L9: =IF(OR(Table1[[#This Row],[Does not regard DAIC-WOZ]]=TRUE,Table1[[#This Row],[Does not use MAE]]=TRUE,Table1[[#This Row],[Does not introduce new model]]=TRUE,Table1[[#This Row],[Not in English]]=TRUE,Table1[[#This Row],[Not retrieved]]=TRUE),TRUE,FALSE) -> FALSE | M9: Uses pretraining on TSATC. Extracts features from auto-selected text fragments | N9: 107 interviews for training, 35 for testing | O9: Interview | P9: Hierarchical Attention Network | Q9: - | R9: - | T9: T | U9: - | V9: - | W9: - | X9: 4.08 | Y9: 5.13 | Z9: - | AA9: No | AB9: No | AC9: Yes | AD9: Yes | AF9: =IF(NOT(Table1[[#This Row],[Data modality]] = ""), NOT(OR(Table1[[#This Row],[Data preprocessing]] = "-", Table1[[#This Row],[Data partitioning]] = "-", Table1[[#This Row],[Partitions disjoint level]] = "-", Table1[[#This Row],[Model description]] ="-", Table1[[#This Row],[Training details]] = "-", Table1[[#This Row],[Final model selection]] = "-", Table1[[#This Row],[Discarded after full-text review]])),"") -> FALSE | AG9: No information on convergence criteria for HAN pretraining. Randomly sampled QA pairs for knowledge transfer, which implies participant inter-partition leakage
A10: FPT-Former: A Flexible Parallel Transformer of Recognizing Depression by Using Audiovisual Expert-Knowledge-Based Multimodal Measures | B10: https://doi.org/10.1155/2024/1564574 | C10: Scopus | D10: Background and Objective. Currently, depression is a widespread global issue that imposes a significant burden and disability on individuals, families, and society. Deep learning (DL) has emerged as a valuable approach for automatically detecting depression by extracting cues from audiovisual data and making a diagnosis. PHQ-8 is considered a validated diagnostic tool for depressive disorders in clinical studies, and the objective of this experiment is to improve the accuracy of PHQ-8 prediction. Furthermore, this paper aims to demonstrate the effectiveness of expert knowledge in depression diagnosis and discuss a novel multimodal network architecture. Methods. This research paper focuses on multimodal depression analysis, proposing a flexible parallel transformer (FPT) model capable of extracting data from three distinct modalities (i.e., one video and two audio descriptors). The FPT-Former model incorporates three paths, each using expert-knowledge-based descriptors from one modality as inputs. These descriptors are represented into 32 features by the encoder part of a transformer module, and these features are fused to realize the final regression of PHQ-8 score. The extended distress analysis interview corpus (E-DAIC) is an expansion of WOZ-DAIC which comprises semiclinical interviews intended to assist in the diagnosis of psychological distress conditions. It encompasses a sample size of 275 participants, and in this study, it was utilized to test the model in a way of 10-fold cross-validation. Results. The FPT presented herein achieved comparable performance to the state-of-the-art works, with a root mean square error (RMSE) of 4.80 and a mean absolute error (MAE) of 4.58. The ablation experiments demonstrate that the three-modality-fused model outperforms other two-modality-fused and single-modality models. While using a PHQ-8 score threshold of 10, the accuracy of the depression classification is 0.79. Conclusions. Leveraging the strength of expert-knowledge-based multimodal measures and parallel transformer structure, the FPT model exhibits promising performance in depression detection. This model improved the accuracy of depression diagnosis through audio and video, and it also proved the effectiveness of using expert-knowledge in the diagnosis of depression. The traits of flexible structure, high predictive efficiency, and secure privacy protection make our model a promotable intelligent system in mental healthcare. © 2024 Yifu Li et al. | E10: FALSE | F10: E-DAIC | G10: TRUE | L10: =IF(OR(Table1[[#This Row],[Does not regard DAIC-WOZ]]=TRUE,Table1[[#This Row],[Does not use MAE]]=TRUE,Table1[[#This Row],[Does not introduce new model]]=TRUE,Table1[[#This Row],[Not in English]]=TRUE,Table1[[#This Row],[Not retrieved]]=TRUE),TRUE,FALSE) -> TRUE | AF10: =IF(NOT(Table1[[#This Row],[Data modality]] = ""), NOT(OR(Table1[[#This Row],[Data preprocessing]] = "-", Table1[[#This Row],[Data partitioning]] = "-", Table1[[#This Row],[Partitions disjoint level]] = "-", Table1[[#This Row],[Model description]] ="-", Table1[[#This Row],[Training details]] = "-", Table1[[#This Row],[Final model selection]] = "-", Table1[[#This Row],[Discarded after full-text review]])),"")
A11: Improving depression prediction using a novel feature selection algorithm coupled with context-aware analysis | B11: https://doi.org/10.1016/j.jad.2021.09.001 | C11: ScienceDirect | D11: Background: Developing machine learning based depression prediction method with information from long-term recordings is important and challenging to clinical diagnosis of depression. Methods: We developed a novel two-stage feature selection algorithm conducted on the high-dimensional (over thirty thousand) features constructed by a context-aware analysis on the data set of DAIC-WOZ, including audio, video, and semantic features. The prediction performance was compared with seven reference models. The preferred topics and feature categories related to the retained features were also analyzed respectively. Results: Parsimonious subsets (tens of features) were selected by the proposed method in each case of prediction. We obtained the best performance in depression classification with F1-score as 0.96 (0.67), Precision as 1.00 (0.63), and Recall as 0.92 (0.71) on the development set (test set). We also achieved promising results in depression severity estimation with RMSE as 4.43 (5.11) and MAE as 3.22 (3.98), having a marginal difference with the best reference model (random forest with ‘Selected-Text’ features). Five most important topics related to depression were revealed. The audio features were predominant to the other feature categories in depression classification while the contributions of the three feature categories to severity estimation were almost equal. Limitations: More depression samples in the database we used should be further included. The second stage of feature selection is relatively time-consuming. Conclusion: This pipeline of depression recognition as well as the preferred topics and feature categories are expected to be useful in supporting the diagnosis of psychological distress conditions. | E11: FALSE | L11: =IF(OR(Table1[[#This Row],[Does not regard DAIC-WOZ]]=TRUE,Table1[[#This Row],[Does not use MAE]]=TRUE,Table1[[#This Row],[Does not introduce new model]]=TRUE,Table1[[#This Row],[Not in English]]=TRUE,Table1[[#This Row],[Not retrieved]]=TRUE),TRUE,FALSE) -> FALSE | M11: Topic-based feature selection | N11: 107 interviews for training, 33 for development, 46 for testing | O11: Interview | P11: SVM | Q11: + | R11: - | T11: V-A-T | U11: 3.22 | V11: 4.43 | W11: - | X11: 3.98 | Y11: 5.11 | Z11: - | AA11: Yes | AB11: Yes | AC11: Yes | AD11: No | AF11: =IF(NOT(Table1[[#This Row],[Data modality]] = ""), NOT(OR(Table1[[#This Row],[Data preprocessing]] = "-", Table1[[#This Row],[Data partitioning]] = "-", Table1[[#This Row],[Partitions disjoint level]] = "-", Table1[[#This Row],[Model description]] ="-", Table1[[#This Row],[Training details]] = "-", Table1[[#This Row],[Final model selection]] = "-", Table1[[#This Row],[Discarded after full-text review]])),"") -> FALSE | AG11: Grid search on train-val split is mentioned, however target metric used for best hyperparameter combination selection is not disclosed. Topics extraction from Interviewer' responses was performed on entire DAIC corpus and not exclusively on training set. Strongly relies on Interviewer's responses
A12: Multi-feature deep supervised voiceprint adversarial network for depression recognition from speech | B12: https://doi.org/10.1016/j.bspc.2023.105704 | C12: ScienceDirect | D12: Depression can induce a range of physiological effects, leading to notable distinctions in the acoustic characteristics exhibited by individuals with depression as opposed to those without. Designing efficient algorithms to accurately identify depression through speech poses a formidable challenge. In this paper, we propose the Multi-Feature Deep Supervised Voiceprint Adversarial Network (MFDS-VAN) for audio-based depression recognition. The MFDS-VAN assimilates extracted acoustic features and the audio waveform, subsequently generating predictions regarding the depression score. In order to attain more robust and discriminative spatial–temporal features associated with depression, the Encoding Network module merges long-term and short-term acoustic features with the unprocessed audio waveform, while the Regression Network module enables the prediction of the depression score. The Deep Supervised Regression algorithm is designed by combining GE2E clustering and Huber regression for better network optimization. Furthermore, to enhance the representation of the MFDS-VAN while diminishing the influence of individual voiceprint information, we propose the Voiceprint Adversarial Network. Experimental results conducted on AVEC 2013, AVEC 2014, and AVEC 2017 datasets demonstrate that the MFDS-VAN significantly enhances robustness and performance in speech-based depression recognition. Our model achieves competitive results when compared to recent audio-based methodologies. | E12: FALSE | F12: AVEC 2013, AVEC 2014, and AVEC 2017 | G12: TRUE | L12: =IF(OR(Table1[[#This Row],[Does not regard DAIC-WOZ]]=TRUE,Table1[[#This Row],[Does not use MAE]]=TRUE,Table1[[#This Row],[Does not introduce new model]]=TRUE,Table1[[#This Row],[Not in English]]=TRUE,Table1[[#This Row],[Not retrieved]]=TRUE),TRUE,FALSE) -> TRUE | AF12: =IF(NOT(Table1[[#This Row],[Data modality]] = ""), NOT(OR(Table1[[#This Row],[Data preprocessing]] = "-", Table1[[#This Row],[Data partitioning]] = "-", Table1[[#This Row],[Partitions disjoint level]] = "-", Table1[[#This Row],[Model description]] ="-", Table1[[#This Row],[Training details]] = "-", Table1[[#This Row],[Final model selection]] = "-", Table1[[#This Row],[Discarded after full-text review]])),"")
A13: PIE: A Personalized Information Embedded model for text-based depression detection | B13: https://doi.org/10.1016/j.ipm.2024.103830 | C13: ScienceDirect | D13: Depression detection based on text analysis has emerged as a research hotspot. Existing research indicates that patients’ personalized characteristics are the primary factor contributing to differences in reported experiences, which poses challenges for automated depression detection methods. To address this, we pioneered defining the fundamental components of personalized information within the text-based depression detection field and proposed the Personalized Information Embedding (PIE) model. The model narrows the gap between generic clinical symptoms and personalized patient experiences in detection, introducing a novel method for computing personalized information representations. Then, we constructed a unique depression intervention dataset containing 108 cases of subjects, the first longitudinally gathering experimental dataset in text-based depression detection. Extensive experimental evidence demonstrates that compared to advanced models, PIE demonstrates statistically significant improvements in performance (with the maximum reductions in RMSE of 0.309 and MAE of 0.232) and generalizability (with standard deviation reductions in RMSE by 75.43% and MAE by 69.77%), and the out-of-domain generalizability of personalized information representations has been validated on two larger external datasets. Additionally, we conducted case studies to analyze how personalized information leads to improved model capabilities. This research serves as a pilot and reference for developing personalized models in text-based depression detection. | E13: FALSE | F13: custom | G13: TRUE | L13: =IF(OR(Table1[[#This Row],[Does not regard DAIC-WOZ]]=TRUE,Table1[[#This Row],[Does not use MAE]]=TRUE,Table1[[#This Row],[Does not introduce new model]]=TRUE,Table1[[#This Row],[Not in English]]=TRUE,Table1[[#This Row],[Not retrieved]]=TRUE),TRUE,FALSE) -> TRUE | AF13: =IF(NOT(Table1[[#This Row],[Data modality]] = ""), NOT(OR(Table1[[#This Row],[Data preprocessing]] = "-", Table1[[#This Row],[Data partitioning]] = "-", Table1[[#This Row],[Partitions disjoint level]] = "-", Table1[[#This Row],[Model description]] ="-", Table1[[#This Row],[Training details]] = "-", Table1[[#This Row],[Final model selection]] = "-", Table1[[#This Row],[Discarded after full-text review]])),"")
A14: Autoencoder based on cepstrum separation to detect depression from speech | B14: https://doi.org/10.1145/3452940.3453038 | C14: Scopus | D14: Depression has become a common mental disorder that plagues more and more people. This paper uses speech signals to study a method for predicting the degree of depression and help clinicians judge the degree of depression in patients. In this paper, a autoencoder model based on Bidirectional Gated Recurrent Unit (BiGRU) is proposed to extract deep speech features, with the original speech as the network input, the signal after the cepstrum separation as the training target. In this model, we take the original speech as the input of the network, and the homomorphic speech as the training target of the model. The long-term deep features extracted by the model and the short-time shallow features extracted by the Opensmile toolkit were sent into Random Forest (RF) respectively, and finally the Support Vector Regression (SVR) was used for decision fusion recognition. In this paper, experiments are conducted on the DAIC-WOZ data set, and the Root Mean Square Error (RMSE) is 5.68 and the Mean Absolute Error (MAE) is 4.64. © 2020 ACM. | E14: FALSE | L14: =IF(OR(Table1[[#This Row],[Does not regard DAIC-WOZ]]=TRUE,Table1[[#This Row],[Does not use MAE]]=TRUE,Table1[[#This Row],[Does not introduce new model]]=TRUE,Table1[[#This Row],[Not in English]]=TRUE,Table1[[#This Row],[Not retrieved]]=TRUE),TRUE,FALSE) -> FALSE | M14: Interviewer utterance removal, participant utterance concatenation and split into 15s fragments | N14: Random 80/20 train/test split | O14: Concatenated participant turns into 15s audio segments | P14: BiGRU | Q14: - | R14: 50-times repeated experiment | T14: A | U14: 4.64 | V14: 5.68 | W14: - | X14: - | Y14: - | Z14: - | AA14: No | AB14: Yes | AC14: No | AD14: Yes | AF14: =IF(NOT(Table1[[#This Row],[Data modality]] = ""), NOT(OR(Table1[[#This Row],[Data preprocessing]] = "-", Table1[[#This Row],[Data partitioning]] = "-", Table1[[#This Row],[Partitions disjoint level]] = "-", Table1[[#This Row],[Model description]] ="-", Table1[[#This Row],[Training details]] = "-", Table1[[#This Row],[Final model selection]] = "-", Table1[[#This Row],[Discarded after full-text review]])),"") -> FALSE | AG14: No information for convergence criteria, no information on handcrafted features preparation, ambiguous description of train-val-test split
A15: Facial action units guided graph representation learning for multimodal depression detection | B15: https://doi.org/10.1016/j.neucom.2024.129106 | C15: ScienceDirect | D15: Depression has become highly prevalent worldwide. Applying technological solutions to compensate for limited resources is crucial for enabling improved early detection and intervention of depressive emotions. Facial expressions and speech are often utilized to assess depression levels since they contain rich emotional cues. However, the inherent inter-individual variability presented in facial expressions and speech introduces noise and redundancy into these cues. Since Facial Action Units (FAUs) represent identity-free facial muscle movements, we proposed a novel FAU-Guided Fusion (FAU-GF) strategy that extracts less noisy and redundant emotional features from human facial and speech behaviors. Moreover, depressive symptoms manifest in a recurrent, episodic, and intermittent fashion, with disjointed temporal connections. To enhance temporal dependency extraction, we innovatively represent temporal events as a graph structure and designed a Feature-Aware Edge Updater (FAEU) to better model contextual dependencies by learning the edges. Subsequently, we adopted Graph Attention Networks (GAT) to update the nodes and edges. After that, a Temporal Attention (TA) module is constructed to selectively focus on informative affect dynamics for each node. Finally, a Depression Predictor is used to assess the depression severity level. The proposed model was evaluated on the AVEC 2014 and AVEC 2019 datasets. Experimental results demonstrate that our model outperforms existing methods. | E15: FALSE | F15: AVEC2014 AVEC2019 | G15: TRUE | L15: =IF(OR(Table1[[#This Row],[Does not regard DAIC-WOZ]]=TRUE,Table1[[#This Row],[Does not use MAE]]=TRUE,Table1[[#This Row],[Does not introduce new model]]=TRUE,Table1[[#This Row],[Not in English]]=TRUE,Table1[[#This Row],[Not retrieved]]=TRUE),TRUE,FALSE) -> TRUE | AF15: =IF(NOT(Table1[[#This Row],[Data modality]] = ""), NOT(OR(Table1[[#This Row],[Data preprocessing]] = "-", Table1[[#This Row],[Data partitioning]] = "-", Table1[[#This Row],[Partitions disjoint level]] = "-", Table1[[#This Row],[Model description]] ="-", Table1[[#This Row],[Training details]] = "-", Table1[[#This Row],[Final model selection]] = "-", Table1[[#This Row],[Discarded after full-text review]])),"")
A16: RADIANCE: Reliable and interpretable depression detection from speech using transformer | B16: https://doi.org/10.1016/j.compbiomed.2024.109325 | C16: ScienceDirect | D16: Depression is a common but severe mental disorder that adversely impacts the ability of an individual to function normally in their day-to-day life. A majority of depressed individuals remain undiagnosed due to factors such as social stigma and a shortage of healthcare professionals. Consequently, several Machine Learning and Deep Learning (DL) models based on speech have been proposed for automatic depression detection, with the latter generally outperforming the former. However, DL models are blackbox and offer no transparency. In contrast, healthcare professionals prefer models that provide interpretability besides being accurate. In this direction, we propose a method RADIANCE (Reliable AnD InterpretAble depressioN deteCtion transformErs). RADIANCE incorporates a novel FilterBank VIsion Transformer (FBViT) network, which provides the symptoms of depression as interpretable features. Additionally, we employ a novel loss function that handles the class imbalance issue in the datasets. It also incorporates a penalty term that addresses the hierarchy of misclassification errors. We also propose a reliability predictor based on low-level descriptors that provides a reliability score to indicate the trustworthiness of the prediction by FBViT. Furthermore, in contrast to the conventional averaging and majority pooling, RADIANCE consolidates predictions from multiple clips of the input audio by intricately weighing each prediction based on its reliability score, ensuring a more accurate overall prediction. RADIANCE outperforms the state-of-the-art depression detection methods, achieving an accuracy of 89.36%, 80.36%, and 94.44% over the DAIC-WOZ, E-DAIC, and CMDC datasets, respectively. Further, RADIANCE achieves MAE scores of 3.27 and 5.04 on the DAIC-WOZ and E-DAIC datasets, respectively. | E16: FALSE | L16: =IF(OR(Table1[[#This Row],[Does not regard DAIC-WOZ]]=TRUE,Table1[[#This Row],[Does not use MAE]]=TRUE,Table1[[#This Row],[Does not introduce new model]]=TRUE,Table1[[#This Row],[Not in English]]=TRUE,Table1[[#This Row],[Not retrieved]]=TRUE),TRUE,FALSE) -> FALSE | M16: Overlapping sliding window. MEL filterbank | N16: - | O16: Interview | P16: FilterBank VIsion Transformer | Q16: - | R16: Grid search | T16: A | U16: - | V16: - | W16: - | X16: - | Y16: - | Z16: - | AA16: No | AB16: No | AC16: Yes | AD16: - | AF16: =IF(NOT(Table1[[#This Row],[Data modality]] = ""), NOT(OR(Table1[[#This Row],[Data preprocessing]] = "-", Table1[[#This Row],[Data partitioning]] = "-", Table1[[#This Row],[Partitions disjoint level]] = "-", Table1[[#This Row],[Model description]] ="-", Table1[[#This Row],[Training details]] = "-", Table1[[#This Row],[Final model selection]] = "-", Table1[[#This Row],[Discarded after full-text review]])),"") -> FALSE | AG16: No information on dataset partitioning. No details on model training and convergence criteria. Reported results are for unknown partition
A17: A multimodal fusion model with multi-level attention mechanism for depression detection | B17: https://doi.org/10.1016/j.bspc.2022.104561 | C17: ScienceDirect | D17: Depression is a common mental illness that affects the physical and mental health of hundreds of millions of people around the world. Therefore, designing an efficient and robust depression detection model is an urgent research task. In order to fully extract depression features, we systematically analyze audio-visual and text data related to depression, and proposes a multimodal fusion model with multi-level attention mechanism (MFM-Att) for depression detection. The method is mainly divided into two stages: the first stage utilizes two LSTMs and a Bi-LSTM with attention mechanism to learn multi-view audio feature, visual feature and rich text feature, respectively. In the second stage, the output features of the three modalities are sent into the attention fusion network (AttFN) to obtain effective depression information, aiming to make use of the diversity and complementarity between modalities for depression detection. It is worth noting that the multi-level attention mechanism can not only extract valuable depressive features of intra-modality, but also learn the correlations of inter-modality, thereby improving the overall performance of the model by reducing the influence of redundant information. MFM-Att model is evaluated on the DAIC-WOZ dataset, and the result outperforms state-of-the-art models in terms of root mean square error (RMSE). | E17: FALSE | L17: =IF(OR(Table1[[#This Row],[Does not regard DAIC-WOZ]]=TRUE,Table1[[#This Row],[Does not use MAE]]=TRUE,Table1[[#This Row],[Does not introduce new model]]=TRUE,Table1[[#This Row],[Not in English]]=TRUE,Table1[[#This Row],[Not retrieved]]=TRUE),TRUE,FALSE) -> FALSE | M17: - | N17: - | O17: - | P17: Tensor Fusion Network (MLP) | Q17: - | R17: - | T17: V-A-T | U17: - | V17: - | W17: - | X17: - | Y17: - | Z17: - | AA17: No | AB17: No | AC17: - | AD17: - | AF17: =IF(NOT(Table1[[#This Row],[Data modality]] = ""), NOT(OR(Table1[[#This Row],[Data preprocessing]] = "-", Table1[[#This Row],[Data partitioning]] = "-", Table1[[#This Row],[Partitions disjoint level]] = "-", Table1[[#This Row],[Model description]] ="-", Table1[[#This Row],[Training details]] = "-", Table1[[#This Row],[Final model selection]] = "-", Table1[[#This Row],[Discarded after full-text review]])),"") -> FALSE | AG17: Missing information regarding training details (e.g. dropout). Paper describes several hyperparameters combinations but does not disclose final model selection criteria. Vague data preprocessing description. No information on data partitioning and disjoint level
A18: Exploring the Capabilities of a Language Model-Only Approach for Depression Detection in Text Data | B18: https://doi.org/10.1109/BHI58575.2023.10313367 | C18: Scopus | D18: Depression is a prevalent and debilitating mental health condition that requires accurate and efficient detection for timely and effective treatment. In this study, we utilized the E-DAIC (Extended Distress Analysis Interview Corpus-Wizard-of-Oz) dataset, an extended version of the DAIC-WOZ dataset, which consists of semi-clinical interviews conducted by an animated virtual interviewer called Ellie, controlled by a human interviewer in another room. With 275 participants, the E-DAIC dataset represents a valuable resource for investigating depression detection methods. Our aim is to predict PHQ-8 scores through text analysis. Leveraging state-of-the-art speech processing, LLM-based text summarization, and a specialized depression detection module, we demonstrate the transformative potential of language data analysis in enhancing depression screening. By overcoming the limitations of manual feature extraction methods, our automated techniques provide a more efficient and effective means of evaluating depression. In our evaluation, we achieve robust accuracy on the development set of the E-DAIC dataset, with a Mean Absolute Error (MAE) of 3.65 in estimating PHQ-8 scores from recorded interviews. This remarkable performance highlights the efficacy of our approach in automatically predicting depression severity. Our research contributes to the growing evidence supporting the use of LLMs in mental health assessment, showcasing the role of innovative technologies in advancing patient care for depression. © 2023 IEEE. | E18: FALSE | F18: E-DAIC | G18: TRUE | L18: =IF(OR(Table1[[#This Row],[Does not regard DAIC-WOZ]]=TRUE,Table1[[#This Row],[Does not use MAE]]=TRUE,Table1[[#This Row],[Does not introduce new model]]=TRUE,Table1[[#This Row],[Not in English]]=TRUE,Table1[[#This Row],[Not retrieved]]=TRUE),TRUE,FALSE) -> TRUE | AF18: =IF(NOT(Table1[[#This Row],[Data modality]] = ""), NOT(OR(Table1[[#This Row],[Data preprocessing]] = "-", Table1[[#This Row],[Data partitioning]] = "-", Table1[[#This Row],[Partitions disjoint level]] = "-", Table1[[#This Row],[Model description]] ="-", Table1[[#This Row],[Training details]] = "-", Table1[[#This Row],[Final model selection]] = "-", Table1[[#This Row],[Discarded after full-text review]])),"")
A19: Speech-Based Depression Detection System Optimized Using Particle Swarm Optimization | B19: https://doi.org/10.1109/NILES63360.2024.10753199 | C19: Scopus | D19: Depression is a prevalent mental disorder, and accurate diagnosis is essential for effective intervention. Traditional diagnostic methods rely on subjective professional judgment, which can introduce bias. To address this challenge, we propose an optimized model that hybridizes Particle Swarm Optimization (PSO), and deep-learning for depression detection and assessment. Our approach leverages Mel-frequency cepstral coefficients (MFCC), Bidirectional Long Short-Term Memory (BiLSTM), and PSO on the audio data. Experiments on the Distress Analysis Interview Corpus Wizard-of-Oz (DAIC-WOZ) dataset demonstrate significant performance improvements. Our model achieves a Root Mean Square Error (RMSE) of 3.82 and a Mean Absolute Error (MAE) of 3.24, outperforming existing state-of-the-art depression detection methods. © 2024 IEEE. | E19: FALSE | L19: =IF(OR(Table1[[#This Row],[Does not regard DAIC-WOZ]]=TRUE,Table1[[#This Row],[Does not use MAE]]=TRUE,Table1[[#This Row],[Does not introduce new model]]=TRUE,Table1[[#This Row],[Not in English]]=TRUE,Table1[[#This Row],[Not retrieved]]=TRUE),TRUE,FALSE) -> FALSE | M19: - | N19: Default | O19: - | P19: PSO, BiLSTM | Q19: - | R19: - | T19: A | U19: 3.24 | V19: 3.82 | W19: - | X19: - | Y19: - | Z19: - | AA19: No | AB19: No | AC19: - | AD19: No | AF19: =IF(NOT(Table1[[#This Row],[Data modality]] = ""), NOT(OR(Table1[[#This Row],[Data preprocessing]] = "-", Table1[[#This Row],[Data partitioning]] = "-", Table1[[#This Row],[Partitions disjoint level]] = "-", Table1[[#This Row],[Model description]] ="-", Table1[[#This Row],[Training details]] = "-", Table1[[#This Row],[Final model selection]] = "-", Table1[[#This Row],[Discarded after full-text review]])),"") -> FALSE | AG19: MFCC features extraction is weakly described (no information regarding audio preprocessing, lack of windowing description). From data preprocessing it’s unclear whether interviewer’s turns are used for the model training. Partitions disjoint level is not disclosed. Training details are not disclosed (optimizer, learning rate, number of epochs). Convergence criteria are not disclosed.
A20: Enhanced Machine Learning Framework for Autonomous Depression Detection Using Modwave Cepstral Fusion and Stochastic Embedding; [УСОВЕРШЕНСТВОВАННАЯ СИСТЕМА МАШИННОГО ОБУЧЕНИЯ ДЛЯ АВТОНОМНОГО ОБНАРУЖЕНИЯ ДЕПРЕССИИ С ИСПОЛЬЗОВАНИЕМ МОДУЛИРОВАННОГО ВЕЙВЛЕТ-КЕПСТРАЛЬНОГО СЛИЯНИЯ И СТОХАСТИЧЕСКОГО ВСТРАИВАНИЯ] | B20: https://doi.org/10.15622/ia.23.6.7 | C20: Scopus | D20: Depression is a prevalent mental illness that requires autonomous detection systems due to its complexity. Existing machine learning techniques face challenges such as background noise sensitivity, slow adaptation speed, and imbalanced data. To address these limitations, this study proposes a novel ModWave Cepstral Fusion and Stochastic Embedding Framework for depression prediction. Then, the Gain Modulated Wavelet Technique removes background noise and normalises audio signals. Difficulties with generalisation, which results in a lack of interpretability, hinder extracting relevant characteristics from speech. To address these issues, an Auto Cepstral Fusion extracts relevant features from speech, capturing temporal and spectral characteristics caused by background voice. Feature selection becomes imperative when choosing relevant features for classification. Selecting irrelevant features can result in overfitting, the curse of dimensionality, and less robustness to noise. Hence, the Principal Stochastic Embedding technique handles high-dimensional data, minimising noise influence and dimensionality. Furthermore, the XGBoost classifier differentiates between depressed and non-depressed individuals. As a result, the proposed method uses the DAIC-WOZ dataset from USC for detecting depressions, achieving an accuracy of 97.02%, precision of 97.02%, recall of 97.02%, F1-score of 97.02%, RMSE of 2.00, and MAE of 0.9, making it a promising tool for autonomous depression detection. © 2024 St. Petersburg Federal Research Center of the Russian Academy of Sciences. All rights reserved. | E20: FALSE | J20: TRUE | L20: =IF(OR(Table1[[#This Row],[Does not regard DAIC-WOZ]]=TRUE,Table1[[#This Row],[Does not use MAE]]=TRUE,Table1[[#This Row],[Does not introduce new model]]=TRUE,Table1[[#This Row],[Not in English]]=TRUE,Table1[[#This Row],[Not retrieved]]=TRUE),TRUE,FALSE) -> TRUE | AF20: =IF(NOT(Table1[[#This Row],[Data modality]] = ""), NOT(OR(Table1[[#This Row],[Data preprocessing]] = "-", Table1[[#This Row],[Data partitioning]] = "-", Table1[[#This Row],[Partitions disjoint level]] = "-", Table1[[#This Row],[Model description]] ="-", Table1[[#This Row],[Training details]] = "-", Table1[[#This Row],[Final model selection]] = "-", Table1[[#This Row],[Discarded after full-text review]])),"")
A21: Gaze Behavior based Depression Severity Estimation | B21: https://doi.org/10.1109/PRML59573.2023.10348319 | C21: Scopus | D21: Depression is a severe mental illness that affects millions of people's lives Every year, more than 700,000 individuals choose to commit suicide due to depression. Early screening of patients with depression is challenging, making it critical to find methods that can aid doctors in quickly identifying potential patients. Currently, a significant number of depression severity estimation tasks focus on text, speech, and vision, but the exploration of the relationship between eye gaze behavior and depression is incomplete. This paper aims to explore the mapping relationship between eye gaze behavior and depression. We propose an integrated method to estimate depression severity using eye gaze behavior data. We formulate a more reasonable representation of gaze direction by expressing it as the angle of deflection. We employ a deep residual shrinkage network with channel-wise thresholds (DRSN-CW) to process the input gaze sequence and estimate the depression severity score. Moreover, we introduce label distribution learning to represent more fine-grained score information and alleviate the overfitting problem associated with small datasets, enhancing the reliability of depression severity estimation. We train and validate our model on the Distress Analysis Interview Corpus - Wizard of Oz (DAIC-WOZ) dataset, achieving an F1 score of 0.769, and reducing the mean absolute error (MAE) to 3.971 and root mean square error (RMSE) to 5.141. The results demonstrate significant improvement in the depression severity estimation task compared to previous tasks. © 2023 IEEE. | E21: FALSE | L21: =IF(OR(Table1[[#This Row],[Does not regard DAIC-WOZ]]=TRUE,Table1[[#This Row],[Does not use MAE]]=TRUE,Table1[[#This Row],[Does not introduce new model]]=TRUE,Table1[[#This Row],[Not in English]]=TRUE,Table1[[#This Row],[Not retrieved]]=TRUE),TRUE,FALSE) -> FALSE | M21: - | N21: 107 interviews for training and 35 for validation | O21: - | P21: - | Q21: - | R21: - | T21: V | U21: 3.971 | V21: 5.141 | W21: - | X21: - | Y21: - | Z21: - | AA21: No | AB21: No | AC21: No | AD21: No | AF21: =IF(NOT(Table1[[#This Row],[Data modality]] = ""), NOT(OR(Table1[[#This Row],[Data preprocessing]] = "-", Table1[[#This Row],[Data partitioning]] = "-", Table1[[#This Row],[Partitions disjoint level]] = "-", Table1[[#This Row],[Model description]] ="-", Table1[[#This Row],[Training details]] = "-", Table1[[#This Row],[Final model selection]] = "-", Table1[[#This Row],[Discarded after full-text review]])),"") -> FALSE | AG21: Lack of description of validation set preprocessing. Training partition was disjoint into 382 seconds fragments, however validation partition disjoint level is not disclosed. Model hyperparameters are not disclosed (number of layers, dimensionality of each layer, convolutional kernels etc.). Training details are not disclosed (optimizer, learning rate, number of epochs). Training details are not disclosed (optimizer, learning rate, number of epochs)
A22: Enhancing Depression Detection: Employing Autoencoders and Linguistic Feature Analysis with BERT and LSTM Model | B22: https://doi.org/10.1109/RusAutoCon58002.2023.10272795 | C22: Scopus | D22: Depression is an abstinent health ailment that affronts several people globally, affecting a consistent decline in mood resulting in a trivial impact on their emotions. The article centers around the utilization of BERT based features and Autoencoders to identify depression from textual input, while also exploring gender identity variations. The study emphasizes the importance of feature engineering for text data obtained from the DAIC_WOZ benchmark dataset. By employing BERT embeddings, which capture the semantic meaning of text, in combination with Autoencoders and additional quantitative characteristics such as PHQ-8 participant feedback, assessment of absolutist word usage, and gender details, the model's performance is significantly improved. We conduct trials with BERT embeddings that encode the textual meaning to extract text characteristics. These features are subsequently combined using Autoencoders. Our method surpasses the performance of the baseline models, achieving an accuracy of 95.5%. Additionally, the mean absolute error (MAE) is measured at 3.75 and the root mean squared error (RMSE) at 5.02, demonstrating the exceptional performance for binary depression classification. These discoveries reveal the capacity of machine learning in mental health investigation, especially when considering gender disparities. © 2023 IEEE. | E22: FALSE | L22: =IF(OR(Table1[[#This Row],[Does not regard DAIC-WOZ]]=TRUE,Table1[[#This Row],[Does not use MAE]]=TRUE,Table1[[#This Row],[Does not introduce new model]]=TRUE,Table1[[#This Row],[Not in English]]=TRUE,Table1[[#This Row],[Not retrieved]]=TRUE),TRUE,FALSE) -> FALSE | M22: - | N22: 148 interviews for training and 41 for testing | O22: - | P22: - | Q22: - | R22: - | T22: T | U22: 3.75 | V22: 5.02 | W22: 0.76 | X22: - | Y22: - | Z22: - | AA22: No | AB22: No | AC22: - | AD22: No | AF22: =IF(NOT(Table1[[#This Row],[Data modality]] = ""), NOT(OR(Table1[[#This Row],[Data preprocessing]] = "-", Table1[[#This Row],[Data partitioning]] = "-", Table1[[#This Row],[Partitions disjoint level]] = "-", Table1[[#This Row],[Model description]] ="-", Table1[[#This Row],[Training details]] = "-", Table1[[#This Row],[Final model selection]] = "-", Table1[[#This Row],[Discarded after full-text review]])),"") -> FALSE | AG22: Data preprocessing description is poor and chaotic: „To minimize noise in text data, commonly used words such as "and," "the," and "is" that lack significant meaning are usually eliminated”. For some reason correlation analysis is performed within AVEC 2019 dataset. Partitions disjoint level is not disclosed. Inconsistencies in model description. Autors state extraction of „767 embeddings”, supposedly meaning „767 dimensional embeddings”, hovewer BERT model produces 768-dimensional vectors. Number of LSTM layers is not disclosed. Autoencoder dimensionality is not disclosed. Training description lacks details (optimizer, early stopping setting).
A23: A textual-based featuring approach for depression detection using machine learning classifiers and social media texts | B23: https://doi.org/10.1016/j.compbiomed.2021.104499 | C23: ScienceDirect | D23: Depression is one of the leading causes of suicide worldwide. However, a large percentage of cases of depression go undiagnosed and, thus, untreated. Previous studies have found that messages posted by individuals with major depressive disorder on social media platforms can be analysed to predict if they are suffering, or likely to suffer, from depression. This study aims to determine whether machine learning could be effectively used to detect signs of depression in social media users by analysing their social media posts—especially when those messages do not explicitly contain specific keywords such as ‘depression’ or ‘diagnosis’. To this end, we investigate several text preprocessing and textual-based featuring methods along with machine learning classifiers, including single and ensemble models, to propose a generalised approach for depression detection using social media texts. We first use two public, labelled Twitter datasets to train and test the machine learning models, and then another three non-Twitter depression-class-only datasets (sourced from Facebook, Reddit, and an electronic diary) to test the performance of our trained models against other social media sources. Experimental results indicate that the proposed approach is able to effectively detect depression via social media texts even when the training datasets do not contain specific keywords (such as ‘depression’ and ‘diagnose’), as well as when unrelated datasets are used for testing. | E23: TRUE | L23: =IF(OR(Table1[[#This Row],[Does not regard DAIC-WOZ]]=TRUE,Table1[[#This Row],[Does not use MAE]]=TRUE,Table1[[#This Row],[Does not introduce new model]]=TRUE,Table1[[#This Row],[Not in English]]=TRUE,Table1[[#This Row],[Not retrieved]]=TRUE),TRUE,FALSE) -> FALSE | AF23: =IF(NOT(Table1[[#This Row],[Data modality]] = ""), NOT(OR(Table1[[#This Row],[Data preprocessing]] = "-", Table1[[#This Row],[Data partitioning]] = "-", Table1[[#This Row],[Partitions disjoint level]] = "-", Table1[[#This Row],[Model description]] ="-", Table1[[#This Row],[Training details]] = "-", Table1[[#This Row],[Final model selection]] = "-", Table1[[#This Row],[Discarded after full-text review]])),"")
A24: A Multimodal Approach for Detection and Assessment of Depression Using Text, Audio and Video | B24: https://doi.org/10.1007/s43657-023-00152-8 | C24: Scopus | D24: Depression is one of the most common mental disorders, and rates of depression in individuals increase each year. Traditional diagnostic methods are primarily based on professional judgment, which is prone to individual bias. Therefore, it is crucial to design an effective and robust diagnostic method for automated depression detection. Current artificial intelligence approaches are limited in their abilities to extract features from long sentences. In addition, current models are not as robust with large input dimensions. To solve these concerns, a multimodal fusion model comprised of text, audio, and video for both depression detection and assessment tasks was developed. In the text modality, pre-trained sentence embedding was utilized to extract semantic representation along with Bidirectional long short-term memory (BiLSTM) to predict depression. This study also used Principal component analysis (PCA) to reduce the dimensionality of the input feature space and Support vector machine (SVM) to predict depression based on audio modality. In the video modality, Extreme gradient boosting (XGBoost) was employed to conduct both feature selection and depression detection. The final predictions were given by outputs of the different modalities with an ensemble voting algorithm. Experiments on the Distress analysis interview corpus wizard-of-Oz (DAIC-WOZ) dataset showed a great improvement of performance, with a weighted F1 score of 0.85, a Root mean square error (RMSE) of 5.57, and a Mean absolute error (MAE) of 4.48. Our proposed model outperforms the baseline in both depression detection and assessment tasks, and was shown to perform better than other existing state-of-the-art depression detection methods. © International Human Phenome Institutes (Shanghai) 2024. | E24: FALSE | L24: =IF(OR(Table1[[#This Row],[Does not regard DAIC-WOZ]]=TRUE,Table1[[#This Row],[Does not use MAE]]=TRUE,Table1[[#This Row],[Does not introduce new model]]=TRUE,Table1[[#This Row],[Not in English]]=TRUE,Table1[[#This Row],[Not retrieved]]=TRUE),TRUE,FALSE) -> FALSE | M24: Removal of interviewer turns, COVAREP, MFCCs, PCA dimensionality reduction, OpenFACE | N24: Default | O24: Interview | P24: BERT-BiLSTM, SVM, XGBoost | Q24: - | R24: - | T24: V-A-T | U24: 4.48 | V24: 5.57 | W24: - | X24: - | Y24: - | Z24: - | AA24: No | AB24: Yes | AC24: No | AD24: No | AF24: =IF(NOT(Table1[[#This Row],[Data modality]] = ""), NOT(OR(Table1[[#This Row],[Data preprocessing]] = "-", Table1[[#This Row],[Data partitioning]] = "-", Table1[[#This Row],[Partitions disjoint level]] = "-", Table1[[#This Row],[Model description]] ="-", Table1[[#This Row],[Training details]] = "-", Table1[[#This Row],[Final model selection]] = "-", Table1[[#This Row],[Discarded after full-text review]])),"") -> FALSE | AG24: Training details are not disclosed. Convergence criteria for text modality are not disclosed.
A25: Prediction of Depression Severity Based on Transformer Encoder and CNN Model | B25: https://doi.org/10.1109/ISCSLP57327.2022.10038064 | C25: Scopus | D25: Depression is one of the most common mental health disorders and can lead to suicide in extreme cases. It is crucial to develop and design an automatic depression detection(ADD) model that is objective, effective, and robust. Many works have been done to develop automatic depression detection systems using speech data due to its easy accessibility and privacy. Although most current methods use RNN, it is difficult to capture the long-term dependence of depressed audio due to the gradient explosion/vanish. In this paper, a novel model combining Transformer Encoder and CNN is proposed to address this problem. Experiments on the DAIC-WOZ dataset show that the performance of the algorithm has improved considerably, with a mean absolute error (MAE) of 4.48 and a root mean square error (RMSE) of 5.37. © 2022 IEEE. | E25: FALSE | L25: =IF(OR(Table1[[#This Row],[Does not regard DAIC-WOZ]]=TRUE,Table1[[#This Row],[Does not use MAE]]=TRUE,Table1[[#This Row],[Does not introduce new model]]=TRUE,Table1[[#This Row],[Not in English]]=TRUE,Table1[[#This Row],[Not retrieved]]=TRUE),TRUE,FALSE) -> FALSE | M25: QA extraction, cleanup, eGeMAPS features | N25: - | O25: - | P25: 1D CNN followed by Transformer Encoder | Q25: - | R25: - | T25: A | U25: 4.48 | V25: 5.37 | W25: - | X25: - | Y25: - | Z25: - | AA25: No | AB25: No | AC25: No | AD25: - | AF25: =IF(NOT(Table1[[#This Row],[Data modality]] = ""), NOT(OR(Table1[[#This Row],[Data preprocessing]] = "-", Table1[[#This Row],[Data partitioning]] = "-", Table1[[#This Row],[Partitions disjoint level]] = "-", Table1[[#This Row],[Model description]] ="-", Table1[[#This Row],[Training details]] = "-", Table1[[#This Row],[Final model selection]] = "-", Table1[[#This Row],[Discarded after full-text review]])),"") -> FALSE | AG25: No information on dataset partition used for training and disjoint level. Missing details regarding training (e.g. number of training epochs, convergence criteria)
A26: HCAG: A hierarchical context-aware graph attention model for depression detection | B26: https://doi.org/10.1109/ICASSP39728.2021.9413486 | C26: Scopus | D26: Depression is one of the most common mental health disorders, it’s crucial to design an effective and robust model for automatic depression detection (ADD). Although current approaches rely on extra topic models or manually topic-selection procedures which is time-consuming, they still haven’t thoroughly explored the sufficient context information among clinical interviews. In this paper, we propose HCAG, a novel Hierarchical Context-Aware Graph attention model for ADD. Our model mirrors the hierarchical structure of depression assessment and leverages the Graph Attention Network (GAT) to grasp relational contextual information of text/audio modality. Experiments on the DAIC-WOZ dataset show a great performance improvement, with the F1-score of 0.92, a Mean Absolute Error (MAE) of 2.94, and a Root Mean Square Error (RMSE) of 3.80. To the best of our knowledge, our model outperforms the existing state-of-the-art methods. © 2021 IEEE | E26: FALSE | L26: =IF(OR(Table1[[#This Row],[Does not regard DAIC-WOZ]]=TRUE,Table1[[#This Row],[Does not use MAE]]=TRUE,Table1[[#This Row],[Does not introduce new model]]=TRUE,Table1[[#This Row],[Not in English]]=TRUE,Table1[[#This Row],[Not retrieved]]=TRUE),TRUE,FALSE) -> FALSE | M26: Manual cleaning. QA pairs extraction, MFCCs, eGeMAPS | N26: Default | O26: Interview | P26: Graph Attention Network | Q26: - | R26: Grid search | T26: A-T | U26: 2.94 | V26: 3.8 | W26: - | X26: - | Y26: - | Z26: - | AA26: No | AB26: No | AC26: Yes | AD26: No | AF26: =IF(NOT(Table1[[#This Row],[Data modality]] = ""), NOT(OR(Table1[[#This Row],[Data preprocessing]] = "-", Table1[[#This Row],[Data partitioning]] = "-", Table1[[#This Row],[Partitions disjoint level]] = "-", Table1[[#This Row],[Model description]] ="-", Table1[[#This Row],[Training details]] = "-", Table1[[#This Row],[Final model selection]] = "-", Table1[[#This Row],[Discarded after full-text review]])),"") -> FALSE | AG26: Lack of information regarding training partition and partitoin used for final model selection in grid search
A27: The use of machine learning and deep learning models in detecting depression on social media: A systematic literature review | B27: https://doi.org/10.1016/j.pmip.2024.100125 | C27: ScienceDirect | D27: Depression is regarded as one of the world's primary concerns. Recent researchers use artificial intelligence techniques like machine learning and deep learning to identify depressive symptoms automatically. This literature review focuses on using machine learning and deep learning models in depression detection on social media. Advances in deep learning have improved methods for identifying depression, which is one of the illnesses that affect the health of individuals. Some researchers employ a variety of deep-learning approaches to improve the diagnosis, detection, and prediction of depression to support expert decision-making. The researchers identified the available prediction techniques and tools used to detect, forecast, compare, and classify depression in victims systematically. Twenty-eight (28) articles relevant to machine learning and thirty-two (32) articles linked to deep learning were chosen and considered using boolean keyword searches in different publishing databases and filters. A significant number of the studies, according to the conclusions of the analysis, used machine learning techniques such as decision trees, K-nearest neighbours, naive bayes, random forests, and support vector machines. The deep learning models that are most frequently utilised include convolutional neural networks, long short-term memory, and recurrent neural networks with different datasets to detect subjects suffering from depression using social media data. The datasets used in these studies include Twitter, Facebook, Reddit, tweets from the Kaggle website, and clinic patients’ records. These datasets can include posts, comments, audio, video, images, and interviews. The results of this study revealed that, recently, several approaches have focused on using deep learning for depression detection. The paper highlighted that most research focuses on the detection and identification of depression. Prospects for cutting-edge studies in the detection of depression and other illnesses that are related to health were also suggested. | E27: TRUE | L27: =IF(OR(Table1[[#This Row],[Does not regard DAIC-WOZ]]=TRUE,Table1[[#This Row],[Does not use MAE]]=TRUE,Table1[[#This Row],[Does not introduce new model]]=TRUE,Table1[[#This Row],[Not in English]]=TRUE,Table1[[#This Row],[Not retrieved]]=TRUE),TRUE,FALSE) -> FALSE | AF27: =IF(NOT(Table1[[#This Row],[Data modality]] = ""), NOT(OR(Table1[[#This Row],[Data preprocessing]] = "-", Table1[[#This Row],[Data partitioning]] = "-", Table1[[#This Row],[Partitions disjoint level]] = "-", Table1[[#This Row],[Model description]] ="-", Table1[[#This Row],[Training details]] = "-", Table1[[#This Row],[Final model selection]] = "-", Table1[[#This Row],[Discarded after full-text review]])),"")
A28: Text-guided multimodal depression detection via cross-modal feature reconstruction and decomposition | B28: https://doi.org/10.1016/j.inffus.2024.102861 | C28: ScienceDirect | D28: Depression, a widespread and debilitating mental health disorder, requires early detection to facilitate effective intervention. Automated depression detection integrating audio with text modalities is a challenging yet significant issue due to the information redundancy and inter-modal heterogeneity across modalities. Prior works usually fail to fully learn the interaction of audio–text modalities for depression detection in an explicit manner. To address these issues, this work proposes a novel text-guided multimdoal depression detection method based on a cross-modal feature reconstruction and decomposition framework. The proposed method takes the text modality as the core modality to guide the model to reconstruct comprehensive audio features for cross-modal feature decomposition tasks. Moreover, the designed cross-modal feature reconstruction and decomposition framework aims to disentangle the shared and private features from the text-guided reconstructed comprehensive audio features for subsequent multimodal fusion. Besides, a bi-directional cross-attention module is designed to interactively learn simultaneous and mutual correlations across modalities for feature enhancement. Extensive experiments are performed on the DAIC-WoZ and E-DAIC datasets, and the results show the superiority of the proposed method on multimodal depression detection tasks, outperforming the state-of-the-arts. | E28: FALSE | L28: =IF(OR(Table1[[#This Row],[Does not regard DAIC-WOZ]]=TRUE,Table1[[#This Row],[Does not use MAE]]=TRUE,Table1[[#This Row],[Does not introduce new model]]=TRUE,Table1[[#This Row],[Not in English]]=TRUE,Table1[[#This Row],[Not retrieved]]=TRUE),TRUE,FALSE) -> FALSE | M28: Overlapping sliding window | N28: - | O28: Audio chunk | P28: Transformer based fusion | Q28: + | R28: - | T28: A-T | U28: - | V28: - | W28: - | X28: - | Y28: - | Z28: - | AA28: No | AB28: No | AC28: Yes | AD28: - | AF28: =IF(NOT(Table1[[#This Row],[Data modality]] = ""), NOT(OR(Table1[[#This Row],[Data preprocessing]] = "-", Table1[[#This Row],[Data partitioning]] = "-", Table1[[#This Row],[Partitions disjoint level]] = "-", Table1[[#This Row],[Model description]] ="-", Table1[[#This Row],[Training details]] = "-", Table1[[#This Row],[Final model selection]] = "-", Table1[[#This Row],[Discarded after full-text review]])),"") -> FALSE | AG28: No information regarding data partitioning. Reported results regard unknown partition. No information regarding best model selection criteria (convergence criteria not applicable - constant number of epochs)
A29: What reveals about depression level? The role of multimodal features at the level of interview questions | B29: https://doi.org/10.1016/j.im.2020.103349 | C29: ScienceDirect | D29: Early depression detection can enable timely intervention. Automatic depression detection has relied on features extracted from individual-level data, which may be too coarse to support effective detection. Existing detection models have largely overlooked interview questions commonly used in clinical depression assessment. This research proposes a two-layered multi-modal model for depression detection, which not only extracts features from responses at a level of individual interview questions, but also identifies semantic categories of those questions. The evaluation results demonstrate that the proposed model outperforms the state-of-the-art methods for depression detection. The research findings have broad and cross-disciplinary implications. | E29: TRUE | L29: =IF(OR(Table1[[#This Row],[Does not regard DAIC-WOZ]]=TRUE,Table1[[#This Row],[Does not use MAE]]=TRUE,Table1[[#This Row],[Does not introduce new model]]=TRUE,Table1[[#This Row],[Not in English]]=TRUE,Table1[[#This Row],[Not retrieved]]=TRUE),TRUE,FALSE) -> FALSE | AF29: =IF(NOT(Table1[[#This Row],[Data modality]] = ""), NOT(OR(Table1[[#This Row],[Data preprocessing]] = "-", Table1[[#This Row],[Data partitioning]] = "-", Table1[[#This Row],[Partitions disjoint level]] = "-", Table1[[#This Row],[Model description]] ="-", Table1[[#This Row],[Training details]] = "-", Table1[[#This Row],[Final model selection]] = "-", Table1[[#This Row],[Discarded after full-text review]])),"")
A30: Automated speech-based screening of depression using deep convolutional neural networks | B30: https://doi.org/10.1016/j.procs.2019.12.228 | C30: ScienceDirect | D30: Early detection and treatment of depression is essential in promoting remission, preventing relapse, and reducing the emotional burden of the disease. Current diagnoses are primarily subjective, inconsistent across professionals, and expensive for individuals who may be in urgent need of help. This paper proposes a novel approach to automated depression detection in speech using convolutional neural network (CNN) and multipart interactive training. The model was tested using 2568 voice samples obtained from 77 non-depressed and 30 depressed individuals. In experiment conducted, data were applied to residual CNNs in the form of spectrograms—images auto-generated from audio samples. The experimental results obtained using different ResNet architectures gave a promising baseline accuracy reaching 77%. | E30: TRUE | L30: =IF(OR(Table1[[#This Row],[Does not regard DAIC-WOZ]]=TRUE,Table1[[#This Row],[Does not use MAE]]=TRUE,Table1[[#This Row],[Does not introduce new model]]=TRUE,Table1[[#This Row],[Not in English]]=TRUE,Table1[[#This Row],[Not retrieved]]=TRUE),TRUE,FALSE) -> FALSE | AF30: =IF(NOT(Table1[[#This Row],[Data modality]] = ""), NOT(OR(Table1[[#This Row],[Data preprocessing]] = "-", Table1[[#This Row],[Data partitioning]] = "-", Table1[[#This Row],[Partitions disjoint level]] = "-", Table1[[#This Row],[Model description]] ="-", Table1[[#This Row],[Training details]] = "-", Table1[[#This Row],[Final model selection]] = "-", Table1[[#This Row],[Discarded after full-text review]])),"")
A31: A hierarchical depression detection model based on vocal and emotional cues | B31: https://doi.org/10.1016/j.neucom.2021.02.019 | C31: ScienceDirect | D31: Effective and efficient automatic depression diagnosis is a challenging subject in the field of affective computing. Since speech signals provide useful information for diagnosing depression, in this paper, we propose to extract deep speaker recognition (SR) and speech emotion recognition (SER) features using pretrained models, and combine the two deep speech features to take advantage of the complementary information between the vocal and emotional differences of speakers. In addition, due to the small amount of data for depression recognition and the cost sensitivity of the diagnosis results, we propose a hierarchical depression detection model, in which multiple classifiers are set up prior to a regressor to guide the prediction of depression severity. We test our method on the AVEC 2013 and AVEC 2014 benchmark databases. The results demonstrate that the fusion of deep SR and SER features can improve the prediction performance of the model. The proposed method, using only audio features, can avoid the overfitting problem and achieves better performance than the previous audio-based methods on both databases. It also provides results comparable to those of video-based and multimodal-based methods for depression detection. | E31: FALSE | F31: AVEC2013, AVEC2014 | G31: TRUE | L31: =IF(OR(Table1[[#This Row],[Does not regard DAIC-WOZ]]=TRUE,Table1[[#This Row],[Does not use MAE]]=TRUE,Table1[[#This Row],[Does not introduce new model]]=TRUE,Table1[[#This Row],[Not in English]]=TRUE,Table1[[#This Row],[Not retrieved]]=TRUE),TRUE,FALSE) -> TRUE | AF31: =IF(NOT(Table1[[#This Row],[Data modality]] = ""), NOT(OR(Table1[[#This Row],[Data preprocessing]] = "-", Table1[[#This Row],[Data partitioning]] = "-", Table1[[#This Row],[Partitions disjoint level]] = "-", Table1[[#This Row],[Model description]] ="-", Table1[[#This Row],[Training details]] = "-", Table1[[#This Row],[Final model selection]] = "-", Table1[[#This Row],[Discarded after full-text review]])),"")
A32: A survey on detecting mental disorders with natural language processing: Literature review, trends and challenges | B32: https://doi.org/10.1016/j.cosrev.2024.100654 | C32: ScienceDirect | D32: For years, the scientific community has researched monitoring approaches for the detection of certain mental disorders and risky behaviors, like depression, eating disorders, gambling, and suicidal ideation among others, in order to activate prevention or mitigation strategies and, in severe cases, clinical treatment. Natural Language Processing is one of the most active disciplines dealing with the automatic detection of mental disorders. This paper offers a comprehensive and extensive review of research works on Natural Language Processing applied to the identification of some mental disorders. To this end, we have identified from a literature review, which are the main types of features used to represent the texts, the machine learning algorithms that are preferred or the most targeted social media platforms, among other aspects. Besides, the paper reports on scientific forums and projects focused on the automatic detection of these problems over the most popular social networks. Thus, this compilation provides a broad view of the matter, summarizing main strategies, and significant findings, but, also, recognizing some of the weaknesses in the research works published so far, serving as clues for future research. | E32: TRUE | L32: =IF(OR(Table1[[#This Row],[Does not regard DAIC-WOZ]]=TRUE,Table1[[#This Row],[Does not use MAE]]=TRUE,Table1[[#This Row],[Does not introduce new model]]=TRUE,Table1[[#This Row],[Not in English]]=TRUE,Table1[[#This Row],[Not retrieved]]=TRUE),TRUE,FALSE) -> FALSE | AF32: =IF(NOT(Table1[[#This Row],[Data modality]] = ""), NOT(OR(Table1[[#This Row],[Data preprocessing]] = "-", Table1[[#This Row],[Data partitioning]] = "-", Table1[[#This Row],[Partitions disjoint level]] = "-", Table1[[#This Row],[Model description]] ="-", Table1[[#This Row],[Training details]] = "-", Table1[[#This Row],[Final model selection]] = "-", Table1[[#This Row],[Discarded after full-text review]])),"")
A33: Qualitative Analysis of the Four-Channel, High-Resolution Urethral Pressure Profile of the Female Dog | B33: https://doi.org/10.1016/S0022-5347(17)38930-9 | C33: ScienceDirect | D33: Four-channel urethral pressure profiles (UPP’s) were measured on six female dogs with an improved perfused open tip technique. A four-channel catheter with one side-hole per channel was used to measure four UPP’s simultaneously in different directions. The dynamic properties of the system have been improved significantly by replacing the conventional perfusion system by a pneumo-hydraulic perfusion system, according to the design of Arndorfer. The UPP’s thus obtained consistently show multiple peaks which depend on catheter orientation. These observations are explained in terms of the presence of several symmetrical as well as asymmetrical muscles in and around the canine urethral wall. Clinical application of the developed technique is expected to yield new information on the functional anatomy of the human urethra. (J. Urol, 142: 855–859, 1989) | E33: TRUE | L33: =IF(OR(Table1[[#This Row],[Does not regard DAIC-WOZ]]=TRUE,Table1[[#This Row],[Does not use MAE]]=TRUE,Table1[[#This Row],[Does not introduce new model]]=TRUE,Table1[[#This Row],[Not in English]]=TRUE,Table1[[#This Row],[Not retrieved]]=TRUE),TRUE,FALSE) -> FALSE | AF33: =IF(NOT(Table1[[#This Row],[Data modality]] = ""), NOT(OR(Table1[[#This Row],[Data preprocessing]] = "-", Table1[[#This Row],[Data partitioning]] = "-", Table1[[#This Row],[Partitions disjoint level]] = "-", Table1[[#This Row],[Model description]] ="-", Table1[[#This Row],[Training details]] = "-", Table1[[#This Row],[Final model selection]] = "-", Table1[[#This Row],[Discarded after full-text review]])),"")
A34: Greenhouse Environmental Control System Based on SW-SVR | B34: https://doi.org/10.1016/j.procs.2015.08.249 | C34: ScienceDirect | D34: Greenhouse environmental control systems using sensor networks are becoming more widespread and sophisticated. To match the produce of expert farmers, these systems collect data about cultivation environment and growth situation, and aim to control the environment for cultivating high quality crops. However, with no agriculture experience, it is difficult for system users to set control parameters of several devices properly. In order to reproduce prediction control performed by expert farmers’ cultivation without human intervention, the authors propose a smart greenhouse environmental control system based on sliding window-based support vector regression (SW-SVR). The proposed system performs prediction control based on accurate predictions in real time. SW-SVR is a new machine learning algorithm for time series data prediction. The prediction model automatically adjusts to the current environment periodically, predicts time series data with high accuracy and low computational complexity. The proposed system using SW-SVR enables system users to optimize controls for crops. Meanwhile, since plant growth is related to the photosynthesis and transpiration of leaves, the authors developed wireless scattered light sensors which measure leaf area size indirectly so as to estimate plant growth. Our experimental results, using data of scattered light sensors on-site, outside weather data, and forecast data as independent variables of SW-SVR for hydroponic culture of tomatoes, show the proposed system reduced prediction error of nitrogen absorption amount by 59.44% as Mean Absolute Error (MAE) and 52.89% as Root Mean Squared Error (RMSE) compared with SVR, and reduced training data by 43.07% on average. Furthermore, the sugar content of tomatoes cultivated by the prototype system increased 1.54 times compared with usual tomatoes. | E34: TRUE | L34: =IF(OR(Table1[[#This Row],[Does not regard DAIC-WOZ]]=TRUE,Table1[[#This Row],[Does not use MAE]]=TRUE,Table1[[#This Row],[Does not introduce new model]]=TRUE,Table1[[#This Row],[Not in English]]=TRUE,Table1[[#This Row],[Not retrieved]]=TRUE),TRUE,FALSE) -> FALSE | AF34: =IF(NOT(Table1[[#This Row],[Data modality]] = ""), NOT(OR(Table1[[#This Row],[Data preprocessing]] = "-", Table1[[#This Row],[Data partitioning]] = "-", Table1[[#This Row],[Partitions disjoint level]] = "-", Table1[[#This Row],[Model description]] ="-", Table1[[#This Row],[Training details]] = "-", Table1[[#This Row],[Final model selection]] = "-", Table1[[#This Row],[Discarded after full-text review]])),"")
A35: Autofusion: Fusing Multi-Modalities with Interactions | B35: https://doi.org/10.1016/j.procs.2024.09.522 | C35: ScienceDirect | D35: In the context of escalating data flows through diverse channels, multimodal machine learning holds the potential to simultaneously process varied data formats from multiple sources, offering robust solutions for uncertainty in various applications. The study highlights the often under-explored correlation information among data modalities and emphasizes the importance of disentangling enriched interactions for more informed decision-making. This paper navigates the burgeoning field of multimodal artificial intelligence (AI) by proposing Autofusion, a pioneering framework addressing representation learning and fusion challenges. Our proposed approach integrates autoencoder structures to address overfitting issues in unimodal machine learning, simultaneously tackling information balancing challenges. The framework’s application in Alzheimer’s disease detection, using DementiaBank’s Pitt corpus, demonstrates promising results, outperforming unimodal methods and showcasing a substantial advantage over traditional fusion techniques. This research significantly contributes by introducing Autofusion as a comprehensive multimodal machine learning solution, demonstrating its efficacy through DementiaBank’s Pitt corpus to detect Alzheimer’s disease, and shedding light on the influential role of cross-modality interaction for enhanced performance in complex applications. | E35: TRUE | L35: =IF(OR(Table1[[#This Row],[Does not regard DAIC-WOZ]]=TRUE,Table1[[#This Row],[Does not use MAE]]=TRUE,Table1[[#This Row],[Does not introduce new model]]=TRUE,Table1[[#This Row],[Not in English]]=TRUE,Table1[[#This Row],[Not retrieved]]=TRUE),TRUE,FALSE) -> FALSE | AF35: =IF(NOT(Table1[[#This Row],[Data modality]] = ""), NOT(OR(Table1[[#This Row],[Data preprocessing]] = "-", Table1[[#This Row],[Data partitioning]] = "-", Table1[[#This Row],[Partitions disjoint level]] = "-", Table1[[#This Row],[Model description]] ="-", Table1[[#This Row],[Training details]] = "-", Table1[[#This Row],[Final model selection]] = "-", Table1[[#This Row],[Discarded after full-text review]])),"")
A36: Multi-modal Expression Detection (MED): A cutting-edge review of current trends, challenges and solutions | B36: https://doi.org/10.1016/j.engappai.2023.106661 | C36: ScienceDirect | D36: In the process of day-to-day learning, expressions are very vital. Detection of human expressions is growing and has caught the interest of many researchers in the past few years, to facilitate research on Affective Computing. Classification of expressions is necessarily needed to keep focus on several expressions for developing an efficient electronic learning system. This classification can provide several solutions in the application of psychology, human computer interaction, artificial intelligence, education, gaming etc. The core attention of this review is to highlight the most recent algorithms used for the extraction of features from multi-modal datasets and various classifiers that are used in the discipline of Multi-modal expression detection (MED). In this study, we review the literature on MED between 2015 and 2022, focusing mainly on feature extraction and classifier schemes. Their advantages, disadvantages and the entire vision have been discussed in brief. This survey also shows that the efficiency of the MED environment is better as compared to single-modal ones. | E36: TRUE | L36: =IF(OR(Table1[[#This Row],[Does not regard DAIC-WOZ]]=TRUE,Table1[[#This Row],[Does not use MAE]]=TRUE,Table1[[#This Row],[Does not introduce new model]]=TRUE,Table1[[#This Row],[Not in English]]=TRUE,Table1[[#This Row],[Not retrieved]]=TRUE),TRUE,FALSE) -> FALSE | AF36: =IF(NOT(Table1[[#This Row],[Data modality]] = ""), NOT(OR(Table1[[#This Row],[Data preprocessing]] = "-", Table1[[#This Row],[Data partitioning]] = "-", Table1[[#This Row],[Partitions disjoint level]] = "-", Table1[[#This Row],[Model description]] ="-", Table1[[#This Row],[Training details]] = "-", Table1[[#This Row],[Final model selection]] = "-", Table1[[#This Row],[Discarded after full-text review]])),"")
A37: Hybrid depression classification and estimation from audio video and text information | B37: https://doi.org/10.1145/3133944.3133950 | C37: Scopus | D37: In this paper, we design a hybrid depression classification and depression estimation framework from audio, video and text descriptors. It contains three main components: 1) Deep Convolutional Neural Network (DCNN) and Deep Neural Network (DNN) based audio visual multi-modal depression recognition frameworks, trained with depressed and not-depressed participants, respectively; 2) Paragraph Vector (PV), Support Vector Machine (SVM) and Random Forest based depression classification framework from the interview transcripts; 3) A multivariate regression model fusing the audio visual PHQ-8 estimations from the depressed and notdepressed DCNN-DNN models, and the depression classification result from the text information. In the DCNN-DNN based depression estimation framework, audio/video feature descriptors are first input into a DCNN to learn high-level features, which are then fed to a DNN to predict the PHQ-8 score. Initial predictions from the two modalities are fused via a DNN model. In the PV-SVM and Random Forest based depression classification framework, we explore semantic-related text features using PV, as well as global text-features. Experiments have been carried out on the Distress Analysis Interview Corpus - Wizard of Oz (DAIC-WOZ) dataset for the Depression Sub-challenge at the 2017 Audio-Visual Emotion Challenge (AVEC), results show that the proposed depression recognition framework obtains very promising results, with root mean square error (RMSE) as 3.088, mean absolute error (MAE) as 2.477 on the development set, and RMSE as 5.400, MAE as 4.359 on the test set, which are all lower than the baseline results. ©2017 Association for Computing Machinery. | E37: FALSE | L37: =IF(OR(Table1[[#This Row],[Does not regard DAIC-WOZ]]=TRUE,Table1[[#This Row],[Does not use MAE]]=TRUE,Table1[[#This Row],[Does not introduce new model]]=TRUE,Table1[[#This Row],[Not in English]]=TRUE,Table1[[#This Row],[Not retrieved]]=TRUE),TRUE,FALSE) -> FALSE | M37: Selection of 10 longest subject's turns | N37: Default | O37: Participant turn | P37: PV-SVM & CNN late fusion | Q37: - | R37: Grid search on train-val split | T37: V-A-T | U37: 2.477 | V37: 3.088 | W37: - | X37: 4.359 | Y37: 5.4 | Z37: - | AA37: No | AB37: No | AC37: No | AD37: No | AF37: =IF(NOT(Table1[[#This Row],[Data modality]] = ""), NOT(OR(Table1[[#This Row],[Data preprocessing]] = "-", Table1[[#This Row],[Data partitioning]] = "-", Table1[[#This Row],[Partitions disjoint level]] = "-", Table1[[#This Row],[Model description]] ="-", Table1[[#This Row],[Training details]] = "-", Table1[[#This Row],[Final model selection]] = "-", Table1[[#This Row],[Discarded after full-text review]])),"") -> FALSE | AG37: Lack of information regarding pretrainig of PV-SVM process (neither link to the dataset, nor pretraining approach)
A38: Exploring Recurrent Neural Network Models for Depression Detection Through Facial Expressions: A Systematic Literature Review | B38: https://doi.org/10.1109/IC2IE60547.2023.10331094 | C38: Scopus | D38: Major Depressive Disorder (MDD) is a prevalent mental disorder, affecting a significant number of individuals, with estimates reaching 300 million cases worldwide. Currently, the diagnosis of this condition relies heavily on subjective assessments based on the experience of medical professionals. Therefore, researchers have turned to deep learning models to explore the detection of depression. The objective of this review is to gather information on detecting depression based on facial expressions in videos using deep learning techniques. Overall, this research found that RNN models achieved 7.22 MAE for AVEC2014. LSTM models produced 4.83 MAE for DAIC-WOZ, while GRU models achieved an accuracy of 89.77% for DAIC-WOZ. Features like Facial Action Units (FAU), eye gaze, and landmarks show great potential and need to be further analyzed to improve results. Analysis can include applying feature engineering techniques. Aggregation methods, such as mean calculation, are recommended as effective approaches for data processing. This Systematic Literature Review found that facial expressions do have relevant patterns related to MDD. © 2023 IEEE. | E38: TRUE | L38: =IF(OR(Table1[[#This Row],[Does not regard DAIC-WOZ]]=TRUE,Table1[[#This Row],[Does not use MAE]]=TRUE,Table1[[#This Row],[Does not introduce new model]]=TRUE,Table1[[#This Row],[Not in English]]=TRUE,Table1[[#This Row],[Not retrieved]]=TRUE),TRUE,FALSE) -> FALSE | AF38: =IF(NOT(Table1[[#This Row],[Data modality]] = ""), NOT(OR(Table1[[#This Row],[Data preprocessing]] = "-", Table1[[#This Row],[Data partitioning]] = "-", Table1[[#This Row],[Partitions disjoint level]] = "-", Table1[[#This Row],[Model description]] ="-", Table1[[#This Row],[Training details]] = "-", Table1[[#This Row],[Final model selection]] = "-", Table1[[#This Row],[Discarded after full-text review]])),"")
A39: Towards automatic text-based estimation of depression through symptom prediction | B39: https://doi.org/10.1186/s40708-023-00185-9 | C39: Scopus | D39: Major Depressive Disorder (MDD) is one of the most common and comorbid mental disorders that impacts a person’s day-to-day activity. In addition, MDD affects one’s linguistic footprint, which is reflected by subtle changes in speech production. This allows us to use natural language processing (NLP) techniques to build a neural classifier to detect depression from speech transcripts. Typically, current NLP systems discriminate only between the depressed and non-depressed states. This approach, however, disregards the complexity of the clinical picture of depression, as different people with MDD can suffer from different sets of depression symptoms. Therefore, predicting individual symptoms can provide more fine-grained information about a person’s condition. In this work, we look at the depression classification problem through the prism of the symptom network analysis approach, which shifts attention from a categorical analysis of depression towards a personalized analysis of symptom profiles. For that purpose, we trained a multi-target hierarchical regression model to predict individual depression symptoms from patient–psychiatrist interview transcripts from the DAIC-WOZ corpus. Our model achieved results on par with state-of-the-art models on both binary diagnostic classification and depression severity prediction while at the same time providing a more fine-grained overview of individual symptoms for each person. The model achieved a mean absolute error (MAE) from 0.438 to 0.830 on eight depression symptoms and showed state-of-the-art results in binary depression estimation (73.9 macro-F1) and total depression score prediction (3.78 MAE). Moreover, the model produced a symptom correlation graph that is structurally identical to the real one. The proposed symptom-based approach provides more in-depth information about the depressive condition by focusing on the individual symptoms rather than a general binary diagnosis. © 2023, The Author(s). | E39: FALSE | L39: =IF(OR(Table1[[#This Row],[Does not regard DAIC-WOZ]]=TRUE,Table1[[#This Row],[Does not use MAE]]=TRUE,Table1[[#This Row],[Does not introduce new model]]=TRUE,Table1[[#This Row],[Not in English]]=TRUE,Table1[[#This Row],[Not retrieved]]=TRUE),TRUE,FALSE) -> FALSE | M39: Interview is processed as a whole turn-wise | N39: Default | O39: Interview | P39: BiLSTM over S-RoBERTa features | Q39: 200 epochs using AdamW optimizer with the learning rate of 3e−5 and a linear warm-up scheduler | R39: Highest micro-averaged F1-score on the development set | T39: T | U39: 5,51±0,06 | V39: - | W39: - | X39: 5,03±0,09 | Y39: - | Z39: - | AA39: Yes | AB39: Yes | AC39: Yes | AD39: No | AF39: =IF(NOT(Table1[[#This Row],[Data modality]] = ""), NOT(OR(Table1[[#This Row],[Data preprocessing]] = "-", Table1[[#This Row],[Data partitioning]] = "-", Table1[[#This Row],[Partitions disjoint level]] = "-", Table1[[#This Row],[Model description]] ="-", Table1[[#This Row],[Training details]] = "-", Table1[[#This Row],[Final model selection]] = "-", Table1[[#This Row],[Discarded after full-text review]])),"") -> TRUE | AG39: Very good paper. Props for using maMAE. R2 would be also useful. Symptom prediction MAE of 3.78 clearly states that there's no practical applicability (symptoms are assessed on 0-3 scale)
A40: Deducing health cues from biometric data | B40: https://doi.org/10.1016/j.cviu.2022.103438 | C40: ScienceDirect | D40: Medical diagnosis involves the expert opinion of trained health care professionals based on causal inference from medical data. While medical data are typically collected using specialized medical-grade sensors, similar data characteristics useful for medical diagnosis are sometimes present in biometric data (e.g., face images, ocular images, and speech signals). In this paper, we explore the biometrics and medical literature to study the following questions. 1) What kind of health cues are embedded in the commonly utilized forms of audio-visual biometric data? 2) How can these health cues be gleaned from the biometric data, and what kind of diseases can it help diagnose? 3) What are some of the implications of using biometric data for medical diagnosis? | E40: TRUE | L40: =IF(OR(Table1[[#This Row],[Does not regard DAIC-WOZ]]=TRUE,Table1[[#This Row],[Does not use MAE]]=TRUE,Table1[[#This Row],[Does not introduce new model]]=TRUE,Table1[[#This Row],[Not in English]]=TRUE,Table1[[#This Row],[Not retrieved]]=TRUE),TRUE,FALSE) -> FALSE | AF40: =IF(NOT(Table1[[#This Row],[Data modality]] = ""), NOT(OR(Table1[[#This Row],[Data preprocessing]] = "-", Table1[[#This Row],[Data partitioning]] = "-", Table1[[#This Row],[Partitions disjoint level]] = "-", Table1[[#This Row],[Model description]] ="-", Table1[[#This Row],[Training details]] = "-", Table1[[#This Row],[Final model selection]] = "-", Table1[[#This Row],[Discarded after full-text review]])),"")
A41: Chapter One - Mental health impact of COVID-19 and machine learning applications in combating mental disorders: a review | B41: https://doi.org/10.1016/B978-0-323-91196-2.00016-8 | C41: ScienceDirect | D41: Mental disorders are a critical issue in modern society, yet it remains to be consistently neglected. The COVID19 pandemic has made it much more difficult to seek assistance when one needs it. People are feeling increasingly anxious and uncertain about their futures while being socially separated from their friends and relatives. As people continue to quarantine among the limitations imposed by governments, interaction between clinical therapists or social workers and those suffering from mental illness has gotten increasingly limited. Machine learning is a vital approach for allowing virtual analysis of many forms of textual, audio, and visual data for sentiment analysis and understanding the mental health of people utilizing numerous critical parameters in this situation. This chapter aims to provide a systematic review of the current literature investigating COVID-19's impact on mental well-being, as well as studies that explore machine learning and artificial intelligence techniques to detect and treat mental illnesses when traditional therapies are unavailable due to lockdown and social distancing norms imposed. The different machine learning algorithms and deep learning approaches utilized in earlier studies are thoroughly discussed in this chapter. Detailed explanation of the data sources utilized and a review of the types of features investigated in mental disorder identification are included as well. The study's major findings are thoroughly discussed. The obstacles of employing machine learning techniques in biomedical applications are explored, as well as possibilities to enhance and progress the discipline. | E41: TRUE | L41: =IF(OR(Table1[[#This Row],[Does not regard DAIC-WOZ]]=TRUE,Table1[[#This Row],[Does not use MAE]]=TRUE,Table1[[#This Row],[Does not introduce new model]]=TRUE,Table1[[#This Row],[Not in English]]=TRUE,Table1[[#This Row],[Not retrieved]]=TRUE),TRUE,FALSE) -> FALSE | AF41: =IF(NOT(Table1[[#This Row],[Data modality]] = ""), NOT(OR(Table1[[#This Row],[Data preprocessing]] = "-", Table1[[#This Row],[Data partitioning]] = "-", Table1[[#This Row],[Partitions disjoint level]] = "-", Table1[[#This Row],[Model description]] ="-", Table1[[#This Row],[Training details]] = "-", Table1[[#This Row],[Final model selection]] = "-", Table1[[#This Row],[Discarded after full-text review]])),"")
A42: Time prediction based on process mining | B42: https://doi.org/10.1016/j.is.2010.09.001 | C42: ScienceDirect | D42: Process mining allows for the automated discovery of process models from event logs. These models provide insights and enable various types of model-based analysis. This paper demonstrates that the discovered process models can be extended with information to predict the completion time of running instances. There are many scenarios where it is useful to have reliable time predictions. For example, when a customer phones her insurance company for information about her insurance claim, she can be given an estimate for the remaining processing time. In order to do this, we provide a configurable approach to construct a process model, augment this model with time information learned from earlier instances, and use this to predict e.g., the completion time. To provide meaningful time predictions we use a configurable set of abstractions that allow for a good balance between “overfitting” and “underfitting”. The approach has been implemented in ProM and through several experiments using real-life event logs we demonstrate its applicability. | E42: TRUE | L42: =IF(OR(Table1[[#This Row],[Does not regard DAIC-WOZ]]=TRUE,Table1[[#This Row],[Does not use MAE]]=TRUE,Table1[[#This Row],[Does not introduce new model]]=TRUE,Table1[[#This Row],[Not in English]]=TRUE,Table1[[#This Row],[Not retrieved]]=TRUE),TRUE,FALSE) -> FALSE | AF42: =IF(NOT(Table1[[#This Row],[Data modality]] = ""), NOT(OR(Table1[[#This Row],[Data preprocessing]] = "-", Table1[[#This Row],[Data partitioning]] = "-", Table1[[#This Row],[Partitions disjoint level]] = "-", Table1[[#This Row],[Model description]] ="-", Table1[[#This Row],[Training details]] = "-", Table1[[#This Row],[Final model selection]] = "-", Table1[[#This Row],[Discarded after full-text review]])),"")
A43: Multimodal Machine Learning for Mental Disorder Detection:A Scoping Review | B43: https://doi.org/10.1016/j.procs.2023.10.134 | C43: ScienceDirect | D43: Recent advancements in machine learning and multimedia technologies have paved new ways for automatic medical diagnosis. In mental health, multimodal inputs such as visual and audible sensing data are promising to investigate the underlying mechanisms of many conditions, such as depression and bipolar disorders. With the increasing burden on healthcare systems, timely diagnosis of mental diseases using multiple modalities might benefit millions of people worldwide. This scoping review provides an exploratory overview of recent multimodal machine learning approaches for mental disorder screening. We also discuss a generalised end-to-end multimodal machine learning pipeline for future research and development of multimodal disease detection. | E43: TRUE | L43: =IF(OR(Table1[[#This Row],[Does not regard DAIC-WOZ]]=TRUE,Table1[[#This Row],[Does not use MAE]]=TRUE,Table1[[#This Row],[Does not introduce new model]]=TRUE,Table1[[#This Row],[Not in English]]=TRUE,Table1[[#This Row],[Not retrieved]]=TRUE),TRUE,FALSE) -> FALSE | AF43: =IF(NOT(Table1[[#This Row],[Data modality]] = ""), NOT(OR(Table1[[#This Row],[Data preprocessing]] = "-", Table1[[#This Row],[Data partitioning]] = "-", Table1[[#This Row],[Partitions disjoint level]] = "-", Table1[[#This Row],[Model description]] ="-", Table1[[#This Row],[Training details]] = "-", Table1[[#This Row],[Final model selection]] = "-", Table1[[#This Row],[Discarded after full-text review]])),"")
A44: A New Regression Model for Depression Severity Prediction Based on Correlation among Audio Features Using a Graph Convolutional Neural Network | B44: https://doi.org/10.3390/diagnostics13040727 | C44: Scopus | D44: Recent studies have revealed mutually correlated audio features in the voices of depressed patients. Thus, the voices of these patients can be characterized based on the combinatorial relationships among the audio features. To date, many deep learning–based methods have been proposed to predict the depression severity using audio data. However, existing methods have assumed that the individual audio features are independent. Hence, in this paper, we propose a new deep learning–based regression model that allows for the prediction of depression severity on the basis of the correlation among audio features. The proposed model was developed using a graph convolutional neural network. This model trains the voice characteristics using graph-structured data generated to express the correlation among audio features. We conducted prediction experiments on depression severity using the DAIC-WOZ dataset employed in several previous studies. The experimental results showed that the proposed model achieved a root mean square error (RMSE) of 2.15, a mean absolute error (MAE) of 1.25, and a symmetric mean absolute percentage error of 50.96%. Notably, RMSE and MAE significantly outperformed the existing state-of-the-art prediction methods. From these results, we conclude that the proposed model can be a promising tool for depression diagnosis. © 2023 by the authors. | E44: FALSE | L44: =IF(OR(Table1[[#This Row],[Does not regard DAIC-WOZ]]=TRUE,Table1[[#This Row],[Does not use MAE]]=TRUE,Table1[[#This Row],[Does not introduce new model]]=TRUE,Table1[[#This Row],[Not in English]]=TRUE,Table1[[#This Row],[Not retrieved]]=TRUE),TRUE,FALSE) -> FALSE | M44: COVAREP | N44: Random 80/10/10 train/val/test split | O44: 10 milliseconds | P44: GCN | Q44: - | R44: - | T44: A | U44: 1.25 | V44: 2.15 | W44: - | X44: - | Y44: - | Z44: - | AA44: No | AB44: No | AC44: Yes | AD44: Yes | AF44: =IF(NOT(Table1[[#This Row],[Data modality]] = ""), NOT(OR(Table1[[#This Row],[Data preprocessing]] = "-", Table1[[#This Row],[Data partitioning]] = "-", Table1[[#This Row],[Partitions disjoint level]] = "-", Table1[[#This Row],[Model description]] ="-", Table1[[#This Row],[Training details]] = "-", Table1[[#This Row],[Final model selection]] = "-", Table1[[#This Row],[Discarded after full-text review]])),"") -> FALSE | AG44: Lack of training-related details (number of epochs, batch size, etc.) and convergence criteria
A45: Progress, achievements, and challenges in multimodal sentiment analysis using deep learning: A survey | B45: https://doi.org/10.1016/j.asoc.2023.111206 | C45: ScienceDirect | D45: Sentiment analysis is a computational technique that analyses the subjective information conveyed within a given expression. This encompasses appraisals, opinions, attitudes or emotions towards a particular subject, individual, or entity. Conventional sentiment analysis solely considers the text modality and derives sentiment by identifying the semantic relationship between words within a sentence. Despite this, certain expressions, such as exaggeration, sarcasm and humor, pose a challenge for automated detection when conveyed only through text. Multimodal sentiment analysis incorporates various forms of data, such as visual and acoustic cues, in addition to text. By utilizing fusion analysis, this approach can more precisely determine the implied sentiment polarity, which includes positive, neutral, and negative sentiments. Thus, the recent advancements in deep learning have boosted the domain of multimodal sentiment analysis to new heights. The research community has also shown significant interest in this topic due to its potential for both practical application and educational research. In light of this fact, this paper aims to present a thorough analysis of recent ground-breaking research studies conducted in multimodal sentiment analysis, which employs deep learning models across various modalities such as text, audio, image, and video. Furthermore, the article dives into a discussion of the multiple categories of multimodal data, diverse domains in which multimodal sentiment analysis can be applied, a range of operations that are integral to multimodal sentiment analysis, deep learning architectures, a variety of fusion methods, challenges associated with multimodal sentiment analysis, and the benchmark datasets in addition to the state-of-the-art approaches. The ultimate goal of this survey is to indicate the success of deep learning architectures in tackling the complexities associated with multimodal sentiment analysis. | E45: TRUE | L45: =IF(OR(Table1[[#This Row],[Does not regard DAIC-WOZ]]=TRUE,Table1[[#This Row],[Does not use MAE]]=TRUE,Table1[[#This Row],[Does not introduce new model]]=TRUE,Table1[[#This Row],[Not in English]]=TRUE,Table1[[#This Row],[Not retrieved]]=TRUE),TRUE,FALSE) -> FALSE | AF45: =IF(NOT(Table1[[#This Row],[Data modality]] = ""), NOT(OR(Table1[[#This Row],[Data preprocessing]] = "-", Table1[[#This Row],[Data partitioning]] = "-", Table1[[#This Row],[Partitions disjoint level]] = "-", Table1[[#This Row],[Model description]] ="-", Table1[[#This Row],[Training details]] = "-", Table1[[#This Row],[Final model selection]] = "-", Table1[[#This Row],[Discarded after full-text review]])),"")
A46: Petrology, geochemistry and U–Pb geochronology of the Betic Ophiolites: Inferences for Pangaea break-up and birth of the westernmost Tethys Ocean | B46: https://doi.org/10.1016/j.lithos.2011.01.002 | C46: ScienceDirect | D46: The Betic Ophiolitic Unit, part of the Mulhacén Complex in the Betic Cordillera (SE Spain), is composed of several tectonic slices of eclogitized mafic and ultramafic rocks, together with oceanic metasediments. A comprehensive review of the petrological characteristics of the Betic Ophiolites shows notable analogies with other ophiolites from the Alps–Apennines system, indicating that they represent relics of oceanic lithosphere created at the westernmost end of the Western Tethys. U–Pb dating by SHRIMP (Sensitive High Resolution Ion MicroProbe) on zircon grains carefully investigated by cathodoluminescence images has been carried out on an eclogitized metagabbro (Lugros outcrop) and a metadolerite dyke intruded in ultramafic rocks (Almirez outcrop), giving consistent magmatic ages of around 185±3Ma. This age marks the beginning of the Betic oceanic magmatism (transitional to enriched MORB) that followed Pangaea break-up and the earliest oceanic accretion of the Western Tethys Ocean. Subsequently, ultraslow mid-ocean ridge spreading developed from the Betic oceanic basin northeastward to the Ligurian and Alpine Tethys domains, mainly around 165 to 140Ma. | E46: TRUE | L46: =IF(OR(Table1[[#This Row],[Does not regard DAIC-WOZ]]=TRUE,Table1[[#This Row],[Does not use MAE]]=TRUE,Table1[[#This Row],[Does not introduce new model]]=TRUE,Table1[[#This Row],[Not in English]]=TRUE,Table1[[#This Row],[Not retrieved]]=TRUE),TRUE,FALSE) -> FALSE | AF46: =IF(NOT(Table1[[#This Row],[Data modality]] = ""), NOT(OR(Table1[[#This Row],[Data preprocessing]] = "-", Table1[[#This Row],[Data partitioning]] = "-", Table1[[#This Row],[Partitions disjoint level]] = "-", Table1[[#This Row],[Model description]] ="-", Table1[[#This Row],[Training details]] = "-", Table1[[#This Row],[Final model selection]] = "-", Table1[[#This Row],[Discarded after full-text review]])),"")
A47: The Biologic and Clinical Significance of Lymphatic Metastases in Breast Cancer | B47: https://doi.org/10.1016/S1055-3207(18)30406-X | C47: ScienceDirect | D47: The best treatment approach for the regional lymph nodes in breast cancer patients continues to undergo debate and reassessment. Most patients with invasive breast cancers are currently being treated by axillary dissections, in part because pathologic staging of the axillary nodes is the most important prognostic factor in patients with primary operable breast cancer and helps select patients for systemic therapy. As is discussed in this article, however, many factors are leading surgeons to become increasingly selective in choosing patients for axillary dissection. Emerging technology may soon lead to accurate axillary staging of many patients without full axillary dissection, and it is quite probable that the role of axillary dissection will continue to be redefined during the next few years. | E47: TRUE | L47: =IF(OR(Table1[[#This Row],[Does not regard DAIC-WOZ]]=TRUE,Table1[[#This Row],[Does not use MAE]]=TRUE,Table1[[#This Row],[Does not introduce new model]]=TRUE,Table1[[#This Row],[Not in English]]=TRUE,Table1[[#This Row],[Not retrieved]]=TRUE),TRUE,FALSE) -> FALSE | AF47: =IF(NOT(Table1[[#This Row],[Data modality]] = ""), NOT(OR(Table1[[#This Row],[Data preprocessing]] = "-", Table1[[#This Row],[Data partitioning]] = "-", Table1[[#This Row],[Partitions disjoint level]] = "-", Table1[[#This Row],[Model description]] ="-", Table1[[#This Row],[Training details]] = "-", Table1[[#This Row],[Final model selection]] = "-", Table1[[#This Row],[Discarded after full-text review]])),"")
A48: Integration of Artificial Intelligence and Wearable Internet of Things for Mental Health Detection | B48: https://doi.org/10.1016/j.ijcce.2024.07.002 | C48: ScienceDirect | D48: The integration of Artificial Intelligence (AI) and Wearable Internet of Things (WIoT) for mental health detection is a promising area of research with the potential to revolutionize mental health monitoring and diagnosis. Since early detection of mental diseases, i.e., depression, is of great importance for diagnosis and treatment, a fast and convenient way is urgently needed. Traditional diagnostic methods are time-consuming, laborious, over-subjective, and easily lead to misdiagnosis. The advance in information techniques and wearable devices brings innovation to mental disease detection. Therefore, this article first compares intelligent depression detection methods and traditional methods to illustrate the significance and then analyzes the opportunities of the wearable device. Then we provide specific psychophysiological data measured by wearable devices and introduce relevant datasets for depression detection. An illustrative example of depression detection with sleep data is presented and discussed and our proposed ensemble method has improved nearly 10% to baselines. Analytical results demonstrate the great potential of using wearable device-measured psychophysiological data to detect depression intelligently. | E48: TRUE | L48: =IF(OR(Table1[[#This Row],[Does not regard DAIC-WOZ]]=TRUE,Table1[[#This Row],[Does not use MAE]]=TRUE,Table1[[#This Row],[Does not introduce new model]]=TRUE,Table1[[#This Row],[Not in English]]=TRUE,Table1[[#This Row],[Not retrieved]]=TRUE),TRUE,FALSE) -> FALSE | AF48: =IF(NOT(Table1[[#This Row],[Data modality]] = ""), NOT(OR(Table1[[#This Row],[Data preprocessing]] = "-", Table1[[#This Row],[Data partitioning]] = "-", Table1[[#This Row],[Partitions disjoint level]] = "-", Table1[[#This Row],[Model description]] ="-", Table1[[#This Row],[Training details]] = "-", Table1[[#This Row],[Final model selection]] = "-", Table1[[#This Row],[Discarded after full-text review]])),"")
A49: Chapter 11 - All about human-robot interaction | B49: https://doi.org/10.1016/B978-0-323-85769-7.00010-0 | C49: ScienceDirect | D49: The latest developments in science and technology has led to the expansion and deployment of robots in various applications covering all spheres of the human life. This necessitates the interaction of humans with robots on a larger scale, as past evidence suggests the robots are considered more as companions rather than machines/tools. Human-computer interaction (HCI) provides insights in understanding and improving interactions with computer-based technologies. However, human-robot interaction (HRI) takes a cue from HCI by introducing autonomy, physical proximity and ability to take decisions in addition to HCI techniques for a robotic system, which makes HRI a distinct area for research. Taking into consideration the huge number of interactions between human and robots, there is a stringent requirement to standardize and make fixed protocols to ensure the usage of robotic technology in a responsible and principled way. This article illustrates a generalized framework and metric taxonomies for robot design through detailed review of literature. The framework presents an end-to-end product design overview for hobbyists and researchers interested in the general steps to create a fully-autonomous, consumer-focused social robots with perception and reasoning capabilities that aim to achieve high technology readiness. | E49: TRUE | L49: =IF(OR(Table1[[#This Row],[Does not regard DAIC-WOZ]]=TRUE,Table1[[#This Row],[Does not use MAE]]=TRUE,Table1[[#This Row],[Does not introduce new model]]=TRUE,Table1[[#This Row],[Not in English]]=TRUE,Table1[[#This Row],[Not retrieved]]=TRUE),TRUE,FALSE) -> FALSE | AF49: =IF(NOT(Table1[[#This Row],[Data modality]] = ""), NOT(OR(Table1[[#This Row],[Data preprocessing]] = "-", Table1[[#This Row],[Data partitioning]] = "-", Table1[[#This Row],[Partitions disjoint level]] = "-", Table1[[#This Row],[Model description]] ="-", Table1[[#This Row],[Training details]] = "-", Table1[[#This Row],[Final model selection]] = "-", Table1[[#This Row],[Discarded after full-text review]])),"")
A50: Clay mineralogy of Thai soils | B50: https://doi.org/10.1016/S0169-1317(96)00033-6 | C50: ScienceDirect | D50: The wide variety of soils in Thailand results of the interaction between climate, parent rocks, and physiography of the country. This is reflected in the wide variety of clay minerals. The complete country can be divided into five regions: the northern, central, north-east, south-east coast and peninsular region. The soil map of Thailand has been used to define the clay mineral provinces. From a mineralogical point of view eight clay mineral and three other assemblages can be distinguished. The clay mineral assemblages concern: kaolinite; kaolinite and illite; kaolinite and smectite; kaolinite, smectite and illite; kaolinite, illite and smectite; smectite and kaolinite; smectite, kaolinite and illite; kaolinite and gibbsite. The three other land types comprise clay-free/quartz-dominated soils, organic soils and slope complexes. Kaolinite is present in all soils. In oxisols, kaolinite is associated with gibbsite, goethite and hematite. In areas where the parent rock is mica-rich, illite is the dominant clay mineral. Smectite is the dominant clay mineral in areas where brackish water conditions prevailed during soil formation and where high amounts of dissolved ions were present. | E50: TRUE | L50: =IF(OR(Table1[[#This Row],[Does not regard DAIC-WOZ]]=TRUE,Table1[[#This Row],[Does not use MAE]]=TRUE,Table1[[#This Row],[Does not introduce new model]]=TRUE,Table1[[#This Row],[Not in English]]=TRUE,Table1[[#This Row],[Not retrieved]]=TRUE),TRUE,FALSE) -> FALSE | AF50: =IF(NOT(Table1[[#This Row],[Data modality]] = ""), NOT(OR(Table1[[#This Row],[Data preprocessing]] = "-", Table1[[#This Row],[Data partitioning]] = "-", Table1[[#This Row],[Partitions disjoint level]] = "-", Table1[[#This Row],[Model description]] ="-", Table1[[#This Row],[Training details]] = "-", Table1[[#This Row],[Final model selection]] = "-", Table1[[#This Row],[Discarded after full-text review]])),"")
A51: Recognition of Audio Depression Based on Convolutional Neural Network and Generative Antagonism Network Model | B51: https://doi.org/10.1109/ACCESS.2020.2998532 | C51: Scopus | D51: This paper proposes an audio depression recognition method based on convolution neural network and generative antagonism network model. First of all, preprocess the data set, remove the long-term mute segments in the data set, and splice the rest into a new audio file. Then, the features of speech signal, such as Mel-scale Frequency Cepstral Coefficients (MFCCs), short-term energy and spectral entropy, are extracted based on audio difference normalization algorithm. The extracted matrix vector feature data, which represents the unique attributes of the subjects' own voice, is the data base for model training. Then, based on the combination of CNN and GAN, DR AudioNet is used to build the model of depression recognition research. With the help of DR AudioNet, the former model is optimized and the recognition classification is completed through the normalization characteristics of the two adjacent segments before and after the current audio segment. The experimental results on AViD-Corpus and DAIC-WOZ datasets show that the proposed method effectively reduces the depression recognition error compared with other existing methods, and the RMSE and MAE values obtained on the two datasets are better than the comparison algorithm by more than 5%. © 2020 IEEE. | E51: FALSE | L51: =IF(OR(Table1[[#This Row],[Does not regard DAIC-WOZ]]=TRUE,Table1[[#This Row],[Does not use MAE]]=TRUE,Table1[[#This Row],[Does not introduce new model]]=TRUE,Table1[[#This Row],[Not in English]]=TRUE,Table1[[#This Row],[Not retrieved]]=TRUE),TRUE,FALSE) -> FALSE | M51: No-voice fragments removal, splitting, MFCCs | N51: - | O51: 708 milliseconds | P51: CNN-GAN | Q51: - | R51: - | T51: A | U51: - | V51: - | W51: - | X51: - | Y51: - | Z51: - | AA51: No | AB51: No | AC51: Yes | AD51: - | AF51: =IF(NOT(Table1[[#This Row],[Data modality]] = ""), NOT(OR(Table1[[#This Row],[Data preprocessing]] = "-", Table1[[#This Row],[Data partitioning]] = "-", Table1[[#This Row],[Partitions disjoint level]] = "-", Table1[[#This Row],[Model description]] ="-", Table1[[#This Row],[Training details]] = "-", Table1[[#This Row],[Final model selection]] = "-", Table1[[#This Row],[Discarded after full-text review]])),"") -> FALSE | AG51: Lack of training process description. Lack of clear disclosure of the data partitioning. Inconsistencies in reported MAE values in tables with ones in the text
A52: Advancing Mental Health Pre-Screening: A New Custom GPT for Psychological Distress Assessment | B52: https://doi.org/10.1109/CogMI62246.2024.00030 | C52: Scopus | D52: This study introduces’Psycho Analyst’, a custom GPT model based on OpenAI’s GPT-4, optimized for pre-screening mental health disorders. Enhanced with DSM-5, PHQ-8, detailed data descriptions, and extensive training data, the model adeptly decodes nuanced linguistic indicators of mental health disorders. It utilizes a dual-task framework that includes binary classification and a three-stage PHQ-8 score computation involving initial assessment, detailed breakdown, and independent assessment, showcasing refined analytic capabilities. Validation with the DAIC-WOZ dataset reveals F1 and Macro-F1 scores of 0.929 and 0.949, respectively, along with the lowest MAE and RMSE of 2.89 and 3.69 in PHQ-8 scoring. These results highlight the model’s precision and transformative potential in enhancing public mental health support, improving accessibility, cost-effectiveness, and serving as a second opinion for professionals. © 2024 IEEE. | E52: FALSE | L52: =IF(OR(Table1[[#This Row],[Does not regard DAIC-WOZ]]=TRUE,Table1[[#This Row],[Does not use MAE]]=TRUE,Table1[[#This Row],[Does not introduce new model]]=TRUE,Table1[[#This Row],[Not in English]]=TRUE,Table1[[#This Row],[Not retrieved]]=TRUE),TRUE,FALSE) -> FALSE | M52: Interviewer utterance removal, participant utterance concatenation | N52: Default | O52: Interview | P52: Zero-shot GPT-4 | Q52: - | R52: N/A | T52: T | U52: 2.91 | V52: 3.81 | W52: 0.64 | X52: - | Y52: - | Z52: - | AA52: No | AB52: No | AC52: - | AD52: No | AF52: =IF(NOT(Table1[[#This Row],[Data modality]] = ""), NOT(OR(Table1[[#This Row],[Data preprocessing]] = "-", Table1[[#This Row],[Data partitioning]] = "-", Table1[[#This Row],[Partitions disjoint level]] = "-", Table1[[#This Row],[Model description]] ="-", Table1[[#This Row],[Training details]] = "-", Table1[[#This Row],[Final model selection]] = "-", Table1[[#This Row],[Discarded after full-text review]])),"") -> FALSE | AG52: Prompts are not disclosed
A53: Trust as indicator of robot functional and social acceptance. An experimental study on user conformation to iCub answers | B53: https://doi.org/10.1016/j.chb.2016.03.057 | C53: ScienceDirect | D53: To investigate the dynamics of human-robot acceptance, we carried out an experimental study with 56 adult participants and the iCub robot. Trust in the robot has been considered as a main indicator of acceptance and measured by the participants' conformation to the iCub's answers to questions on functional and social tasks characterized by perceptual and socio cognitive uncertainty. In particular, we were interested in understanding whether (i) trust in functional savvy is a prerequisite for trust in social savvy, and (ii) to what extent factors such as participants' desire for control, attitude towards social influence of robots, and imagined collaborative vs. competitive scenario, may influence their trust in the iCub. We found that participants conformed more to the iCub's answers in the functional than in the social tasks. Moreover, the few participants conforming to the iCub's answers in the social task also conformed less in the functional issues. Trust in the robot's functional savvy does not thus seem to be a pre-requisite for trust in its social savvy. Finally, the examined factors did not influence the trust in iCub. Results are discussed with relation to methodology of human-robot interaction (HRI) research. | E53: TRUE | L53: =IF(OR(Table1[[#This Row],[Does not regard DAIC-WOZ]]=TRUE,Table1[[#This Row],[Does not use MAE]]=TRUE,Table1[[#This Row],[Does not introduce new model]]=TRUE,Table1[[#This Row],[Not in English]]=TRUE,Table1[[#This Row],[Not retrieved]]=TRUE),TRUE,FALSE) -> FALSE | AF53: =IF(NOT(Table1[[#This Row],[Data modality]] = ""), NOT(OR(Table1[[#This Row],[Data preprocessing]] = "-", Table1[[#This Row],[Data partitioning]] = "-", Table1[[#This Row],[Partitions disjoint level]] = "-", Table1[[#This Row],[Model description]] ="-", Table1[[#This Row],[Training details]] = "-", Table1[[#This Row],[Final model selection]] = "-", Table1[[#This Row],[Discarded after full-text review]])),"")
A54: Negative home equity reduces household mobility: Evidence from administrative data | B54: https://doi.org/10.1016/j.jhe.2018.06.010 | C54: ScienceDirect | D54: We investigate the impact of negative home equity on household residential mobility. We employ a unique administrative panel data set covering nearly the whole population of Dutch homeowners. The data contains a large set of personal characteristics of more than 2,000,000 homeowners. We identify the effect of negative home equity on mobility by exploiting the quasi-exogenous regional variation of the unanticipated housing market shock during 2008–2012, in which real house prices declined by 25%. Households plunging into negative home equity due to unanticipated declining house prices are 21% less likely to move compared to households upholding positive home equity. | E54: TRUE | L54: =IF(OR(Table1[[#This Row],[Does not regard DAIC-WOZ]]=TRUE,Table1[[#This Row],[Does not use MAE]]=TRUE,Table1[[#This Row],[Does not introduce new model]]=TRUE,Table1[[#This Row],[Not in English]]=TRUE,Table1[[#This Row],[Not retrieved]]=TRUE),TRUE,FALSE) -> FALSE | AF54: =IF(NOT(Table1[[#This Row],[Data modality]] = ""), NOT(OR(Table1[[#This Row],[Data preprocessing]] = "-", Table1[[#This Row],[Data partitioning]] = "-", Table1[[#This Row],[Partitions disjoint level]] = "-", Table1[[#This Row],[Model description]] ="-", Table1[[#This Row],[Training details]] = "-", Table1[[#This Row],[Final model selection]] = "-", Table1[[#This Row],[Discarded after full-text review]])),"")
A55: The Efficacy of Norfloxacin in the Treatment of Chronic Bacterial Prostatitis Refractory to Trimethoprim-Sulfamethoxazole and/or Carbenicillin | B55: https://doi.org/10.1016/S0022-5347(17)39556-3 | C55: ScienceDirect | D55: We treated 15 men who had chronic bacterial prostatitis refractory to trimethoprim-sulfamethoxazole and/or carbenicillin with 400mg. norfloxacin twice daily for 28 days. All pathogens were susceptible to norfloxacin and absent in prostatic fluid cultures obtained during therapy. One patient had negative post-therapy prostatic fluid cultures but was lost to followup at 1 month. Of the 14 patients followed for at least 6 months 9 64%) were cured of the original infection, including 6 who have remained uninfected and have had negative prostatic secretion and urine cultures for at least 2 years 1), 1 year 2) or 6 months 3). In 3 patients urinary tract infections recurred with new pathogens at 6, 560 and 820 days after post-therapy negative prostatic fluid cultures. Bacterial prostatitis with the original pathogen recurred in 5 patients within 2 months of completing therapy. The bacteria remained susceptible to norfloxacin but could not be eradicated with 30 to 90 days of additional norfloxacin therapy. Cures were achieved in 9 of 12 patients with Escherichia coli, none of 2 with Pseudomonas prostatitis and 3 of 5 with prostatic calculi. No patient experienced significant adverse effects. The data suggest that norfloxacin is effective and safe for the treatment of refractory chronic bacterial prostatitis. | E55: TRUE | L55: =IF(OR(Table1[[#This Row],[Does not regard DAIC-WOZ]]=TRUE,Table1[[#This Row],[Does not use MAE]]=TRUE,Table1[[#This Row],[Does not introduce new model]]=TRUE,Table1[[#This Row],[Not in English]]=TRUE,Table1[[#This Row],[Not retrieved]]=TRUE),TRUE,FALSE) -> FALSE | AF55: =IF(NOT(Table1[[#This Row],[Data modality]] = ""), NOT(OR(Table1[[#This Row],[Data preprocessing]] = "-", Table1[[#This Row],[Data partitioning]] = "-", Table1[[#This Row],[Partitions disjoint level]] = "-", Table1[[#This Row],[Model description]] ="-", Table1[[#This Row],[Training details]] = "-", Table1[[#This Row],[Final model selection]] = "-", Table1[[#This Row],[Discarded after full-text review]])),"")
A56: Chapter Eight - Affective computing: Computational Knowledge Vision for depression detection | B56: https://doi.org/10.1016/B978-0-44-321619-0.00016-9 | C56: ScienceDirect | D56: With more than 300 million people depressed worldwide annually, depression is a global problem. The goal of depression detection is to improve diagnostic accuracy and availability, leading to faster intervention. The most important and challenging problem here is to design an effective and robust depression detection model. To this end, there are two challenges to overcome: 1) Multi-modal (audio, image, text, etc.) information must be jointly considered to make accurate inferences. 2) Existing deep learning-based work suffers from multi-modal data sufficiency problem. To address these issues, we propose a graph attention model embedded with multi-modal knowledge for depression detection. This approach learns not only reasonable embeddings for nodes in the knowledge graph, but also exploits medical knowledge to improve the performance of classification and prediction with the knowledge attention mechanism. Experimental results on two real-world datasets show that the proposed approach significantly improves the classification and prediction performance compared with other major state-of-the-art approaches, with guaranteed the robustness with each modality of multi-modal data. Overall, this chapter shows how multi-modal knowledge attention mechanism and deep-learning-based networks can be combined to assist mental health patients and practitioners. | E56: TRUE | L56: =IF(OR(Table1[[#This Row],[Does not regard DAIC-WOZ]]=TRUE,Table1[[#This Row],[Does not use MAE]]=TRUE,Table1[[#This Row],[Does not introduce new model]]=TRUE,Table1[[#This Row],[Not in English]]=TRUE,Table1[[#This Row],[Not retrieved]]=TRUE),TRUE,FALSE) -> FALSE | AF56: =IF(NOT(Table1[[#This Row],[Data modality]] = ""), NOT(OR(Table1[[#This Row],[Data preprocessing]] = "-", Table1[[#This Row],[Data partitioning]] = "-", Table1[[#This Row],[Partitions disjoint level]] = "-", Table1[[#This Row],[Model description]] ="-", Table1[[#This Row],[Training details]] = "-", Table1[[#This Row],[Final model selection]] = "-", Table1[[#This Row],[Discarded after full-text review]])),"")
A57: Deep learning for depression recognition with audiovisual cues: A review | B57: https://doi.org/10.1016/j.inffus.2021.10.012 | C57: ScienceDirect | D57: With the acceleration of the pace of work and life, people are facing more and more pressure, which increases the probability of suffering from depression. However, many patients may fail to get a timely diagnosis due to the serious imbalance in the doctor–patient ratio in the world. A promising development is that physiological and psychological studies have found some differences in speech and facial expression between patients with depression and healthy individuals. Consequently, to improve current medical care, Deep Learning (DL) has been used to extract a representation of depression cues from audio and video for automatic depression detection. To classify and summarize such research, we introduce the databases and describe objective markers for automatic depression estimation. We also review the DL methods for automatic detection of depression to extract a representation of depression from audio and video. Lastly, we discuss challenges and promising directions related to the automatic diagnoses of depression using DL. | E57: TRUE | L57: =IF(OR(Table1[[#This Row],[Does not regard DAIC-WOZ]]=TRUE,Table1[[#This Row],[Does not use MAE]]=TRUE,Table1[[#This Row],[Does not introduce new model]]=TRUE,Table1[[#This Row],[Not in English]]=TRUE,Table1[[#This Row],[Not retrieved]]=TRUE),TRUE,FALSE) -> FALSE | AF57: =IF(NOT(Table1[[#This Row],[Data modality]] = ""), NOT(OR(Table1[[#This Row],[Data preprocessing]] = "-", Table1[[#This Row],[Data partitioning]] = "-", Table1[[#This Row],[Partitions disjoint level]] = "-", Table1[[#This Row],[Model description]] ="-", Table1[[#This Row],[Training details]] = "-", Table1[[#This Row],[Final model selection]] = "-", Table1[[#This Row],[Discarded after full-text review]])),"")
A58: Towards using Breathing Features for Multimodal Estimation of Depression Severity | B58: https://doi.org/10.1145/3536221.3556606 | C58: ACM | E58: TRUE | L58: =IF(OR(Table1[[#This Row],[Does not regard DAIC-WOZ]]=TRUE,Table1[[#This Row],[Does not use MAE]]=TRUE,Table1[[#This Row],[Does not introduce new model]]=TRUE,Table1[[#This Row],[Not in English]]=TRUE,Table1[[#This Row],[Not retrieved]]=TRUE),TRUE,FALSE) -> FALSE | AF58: =IF(NOT(Table1[[#This Row],[Data modality]] = ""), NOT(OR(Table1[[#This Row],[Data preprocessing]] = "-", Table1[[#This Row],[Data partitioning]] = "-", Table1[[#This Row],[Partitions disjoint level]] = "-", Table1[[#This Row],[Model description]] ="-", Table1[[#This Row],[Training details]] = "-", Table1[[#This Row],[Final model selection]] = "-", Table1[[#This Row],[Discarded after full-text review]])),"")
A59: Decision Tree Based Depression Classification from Audio Video and Language Information | B59: https://doi.org/10.1145/2988257.2988269 | C59: ACM | E59: FALSE | L59: =IF(OR(Table1[[#This Row],[Does not regard DAIC-WOZ]]=TRUE,Table1[[#This Row],[Does not use MAE]]=TRUE,Table1[[#This Row],[Does not introduce new model]]=TRUE,Table1[[#This Row],[Not in English]]=TRUE,Table1[[#This Row],[Not retrieved]]=TRUE),TRUE,FALSE) -> FALSE | M59: Manual feature assignment | N59: Default | O59: - | P59: Gender-dependent Decision Tree | Q59: - | R59: - | T59: V-A | U59: - | V59: - | W59: - | X59: 6.702 | Y59: 9.106 | Z59: - | AA59: No | AB59: No | AC59: - | AD59: No | AF59: =IF(NOT(Table1[[#This Row],[Data modality]] = ""), NOT(OR(Table1[[#This Row],[Data preprocessing]] = "-", Table1[[#This Row],[Data partitioning]] = "-", Table1[[#This Row],[Partitions disjoint level]] = "-", Table1[[#This Row],[Model description]] ="-", Table1[[#This Row],[Training details]] = "-", Table1[[#This Row],[Final model selection]] = "-", Table1[[#This Row],[Discarded after full-text review]])),"") -> FALSE | AG59: No information regarding pratitions disjoint level. No clear description of the model architecture used. Manually extracted features
A60: Multimodal Measurement of Depression Using Deep Learning Models | B60: https://doi.org/10.1145/3133944.3133948 | C60: ACM | E60: FALSE | I60: TRUE | L60: =IF(OR(Table1[[#This Row],[Does not regard DAIC-WOZ]]=TRUE,Table1[[#This Row],[Does not use MAE]]=TRUE,Table1[[#This Row],[Does not introduce new model]]=TRUE,Table1[[#This Row],[Not in English]]=TRUE,Table1[[#This Row],[Not retrieved]]=TRUE),TRUE,FALSE) -> TRUE | AF60: =IF(NOT(Table1[[#This Row],[Data modality]] = ""), NOT(OR(Table1[[#This Row],[Data preprocessing]] = "-", Table1[[#This Row],[Data partitioning]] = "-", Table1[[#This Row],[Partitions disjoint level]] = "-", Table1[[#This Row],[Model description]] ="-", Table1[[#This Row],[Training details]] = "-", Table1[[#This Row],[Final model selection]] = "-", Table1[[#This Row],[Discarded after full-text review]])),"")
A61: Leveraging Social Robots to Promote Hand Hygiene: A Cross-Cultural and Socio-Economic Study of Children in Diverse School Settings | C61: ACM | E61: TRUE | L61: =IF(OR(Table1[[#This Row],[Does not regard DAIC-WOZ]]=TRUE,Table1[[#This Row],[Does not use MAE]]=TRUE,Table1[[#This Row],[Does not introduce new model]]=TRUE,Table1[[#This Row],[Not in English]]=TRUE,Table1[[#This Row],[Not retrieved]]=TRUE),TRUE,FALSE) -> FALSE | AF61: =IF(NOT(Table1[[#This Row],[Data modality]] = ""), NOT(OR(Table1[[#This Row],[Data preprocessing]] = "-", Table1[[#This Row],[Data partitioning]] = "-", Table1[[#This Row],[Partitions disjoint level]] = "-", Table1[[#This Row],[Model description]] ="-", Table1[[#This Row],[Training details]] = "-", Table1[[#This Row],[Final model selection]] = "-", Table1[[#This Row],[Discarded after full-text review]])),"")
A62: Proceedings of the 2024 7th International Conference on Digital Medicine and Image Processing | C62: ACM | E62: TRUE | L62: =IF(OR(Table1[[#This Row],[Does not regard DAIC-WOZ]]=TRUE,Table1[[#This Row],[Does not use MAE]]=TRUE,Table1[[#This Row],[Does not introduce new model]]=TRUE,Table1[[#This Row],[Not in English]]=TRUE,Table1[[#This Row],[Not retrieved]]=TRUE),TRUE,FALSE) -> FALSE | AF62: =IF(NOT(Table1[[#This Row],[Data modality]] = ""), NOT(OR(Table1[[#This Row],[Data preprocessing]] = "-", Table1[[#This Row],[Data partitioning]] = "-", Table1[[#This Row],[Partitions disjoint level]] = "-", Table1[[#This Row],[Model description]] ="-", Table1[[#This Row],[Training details]] = "-", Table1[[#This Row],[Final model selection]] = "-", Table1[[#This Row],[Discarded after full-text review]])),"")
A63: Depression Severity Prediction Based on Biomarkers of Psychomotor Retardation | B63: https://doi.org/10.1145/3133944.3133947 | C63: ACM | E63: FALSE | L63: =IF(OR(Table1[[#This Row],[Does not regard DAIC-WOZ]]=TRUE,Table1[[#This Row],[Does not use MAE]]=TRUE,Table1[[#This Row],[Does not introduce new model]]=TRUE,Table1[[#This Row],[Not in English]]=TRUE,Table1[[#This Row],[Not retrieved]]=TRUE),TRUE,FALSE) -> FALSE | M63: Removal of interviewer turns, COVAREP, MFCCs | N63: Default | O63: Interview | P63: GMM, Fisher Vectors | Q63: + | R63: Tthe smallest RMSE on the Development set | T63: V-A | U63: 5.5 | V63: 6.5 | W63: - | X63: 5.42 | Y63: 6.42 | Z63: - | AA63: No | AB63: No | AC63: No | AD63: No | AF63: =IF(NOT(Table1[[#This Row],[Data modality]] = ""), NOT(OR(Table1[[#This Row],[Data preprocessing]] = "-", Table1[[#This Row],[Data partitioning]] = "-", Table1[[#This Row],[Partitions disjoint level]] = "-", Table1[[#This Row],[Model description]] ="-", Table1[[#This Row],[Training details]] = "-", Table1[[#This Row],[Final model selection]] = "-", Table1[[#This Row],[Discarded after full-text review]])),"") -> TRUE | AG63: Very chaotic. No explicit information on data partitioning. We are assuming default partitioning, since the paper is published in AVEC proceedings
A64: Proceedings of the 12th International Conference on Human-Agent Interaction | C64: ACM | E64: TRUE | L64: =IF(OR(Table1[[#This Row],[Does not regard DAIC-WOZ]]=TRUE,Table1[[#This Row],[Does not use MAE]]=TRUE,Table1[[#This Row],[Does not introduce new model]]=TRUE,Table1[[#This Row],[Not in English]]=TRUE,Table1[[#This Row],[Not retrieved]]=TRUE),TRUE,FALSE) -> FALSE | AF64: =IF(NOT(Table1[[#This Row],[Data modality]] = ""), NOT(OR(Table1[[#This Row],[Data preprocessing]] = "-", Table1[[#This Row],[Data partitioning]] = "-", Table1[[#This Row],[Partitions disjoint level]] = "-", Table1[[#This Row],[Model description]] ="-", Table1[[#This Row],[Training details]] = "-", Table1[[#This Row],[Final model selection]] = "-", Table1[[#This Row],[Discarded after full-text review]])),"")
A65: Detecting Depression using Vocal, Facial and Semantic Communication Cues | B65: https://doi.org/10.1145/2988257.2988263 | C65: ACM | E65: FALSE | L65: =IF(OR(Table1[[#This Row],[Does not regard DAIC-WOZ]]=TRUE,Table1[[#This Row],[Does not use MAE]]=TRUE,Table1[[#This Row],[Does not introduce new model]]=TRUE,Table1[[#This Row],[Not in English]]=TRUE,Table1[[#This Row],[Not retrieved]]=TRUE),TRUE,FALSE) -> FALSE | M65: - | N65: Default | O65: - | P65: - | Q65: - | R65: - | T65: V-A-T | U65: 4.18 | V65: 5.31 | W65: - | X65: - | Y65: - | Z65: - | AA65: No | AB65: No | AC65: Yes | AD65: - | AF65: =IF(NOT(Table1[[#This Row],[Data modality]] = ""), NOT(OR(Table1[[#This Row],[Data preprocessing]] = "-", Table1[[#This Row],[Data partitioning]] = "-", Table1[[#This Row],[Partitions disjoint level]] = "-", Table1[[#This Row],[Model description]] ="-", Table1[[#This Row],[Training details]] = "-", Table1[[#This Row],[Final model selection]] = "-", Table1[[#This Row],[Discarded after full-text review]])),"") -> FALSE | AG65: Very chaotic. Though for audio preprocessing the interviewer turns are removed from the recordig, text modality based classification strongly relies on interviewer prompts. Very chaotic desctiption of models used per modality and their ensemble
A66: Multi-modality Depression Detection via Multi-scale Temporal Dilated CNNs | B66: https://doi.org/10.1145/3347320.3357695 | C66: ACM | E66: FALSE | F66: AVEC2019 | G66: TRUE | L66: =IF(OR(Table1[[#This Row],[Does not regard DAIC-WOZ]]=TRUE,Table1[[#This Row],[Does not use MAE]]=TRUE,Table1[[#This Row],[Does not introduce new model]]=TRUE,Table1[[#This Row],[Not in English]]=TRUE,Table1[[#This Row],[Not retrieved]]=TRUE),TRUE,FALSE) -> TRUE | AF66: =IF(NOT(Table1[[#This Row],[Data modality]] = ""), NOT(OR(Table1[[#This Row],[Data preprocessing]] = "-", Table1[[#This Row],[Data partitioning]] = "-", Table1[[#This Row],[Partitions disjoint level]] = "-", Table1[[#This Row],[Model description]] ="-", Table1[[#This Row],[Training details]] = "-", Table1[[#This Row],[Final model selection]] = "-", Table1[[#This Row],[Discarded after full-text review]])),"")
A67: Multi-level Attention Network using Text, Audio and Video for Depression Prediction | B67: https://doi.org/10.1145/3347320.3357697 | C67: ACM | E67: FALSE | F67: AVEC2019 | G67: TRUE | L67: =IF(OR(Table1[[#This Row],[Does not regard DAIC-WOZ]]=TRUE,Table1[[#This Row],[Does not use MAE]]=TRUE,Table1[[#This Row],[Does not introduce new model]]=TRUE,Table1[[#This Row],[Not in English]]=TRUE,Table1[[#This Row],[Not retrieved]]=TRUE),TRUE,FALSE) -> TRUE | AF67: =IF(NOT(Table1[[#This Row],[Data modality]] = ""), NOT(OR(Table1[[#This Row],[Data preprocessing]] = "-", Table1[[#This Row],[Data partitioning]] = "-", Table1[[#This Row],[Partitions disjoint level]] = "-", Table1[[#This Row],[Model description]] ="-", Table1[[#This Row],[Training details]] = "-", Table1[[#This Row],[Final model selection]] = "-", Table1[[#This Row],[Discarded after full-text review]])),"")
A68: Understanding User Perceptions, Collaborative Experience and User Engagement in Different Human-AI Interaction Designs for Co-Creative Systems | B68: https://doi.org/10.1145/3527927.3532789 | C68: ACM | E68: TRUE | L68: =IF(OR(Table1[[#This Row],[Does not regard DAIC-WOZ]]=TRUE,Table1[[#This Row],[Does not use MAE]]=TRUE,Table1[[#This Row],[Does not introduce new model]]=TRUE,Table1[[#This Row],[Not in English]]=TRUE,Table1[[#This Row],[Not retrieved]]=TRUE),TRUE,FALSE) -> FALSE | AF68: =IF(NOT(Table1[[#This Row],[Data modality]] = ""), NOT(OR(Table1[[#This Row],[Data preprocessing]] = "-", Table1[[#This Row],[Data partitioning]] = "-", Table1[[#This Row],[Partitions disjoint level]] = "-", Table1[[#This Row],[Model description]] ="-", Table1[[#This Row],[Training details]] = "-", Table1[[#This Row],[Final model selection]] = "-", Table1[[#This Row],[Discarded after full-text review]])),"")
A69: Proceedings of the IEEE/ACM 46th International Conference on Software Engineering | C69: ACM | E69: TRUE | L69: =IF(OR(Table1[[#This Row],[Does not regard DAIC-WOZ]]=TRUE,Table1[[#This Row],[Does not use MAE]]=TRUE,Table1[[#This Row],[Does not introduce new model]]=TRUE,Table1[[#This Row],[Not in English]]=TRUE,Table1[[#This Row],[Not retrieved]]=TRUE),TRUE,FALSE) -> FALSE | AF69: =IF(NOT(Table1[[#This Row],[Data modality]] = ""), NOT(OR(Table1[[#This Row],[Data preprocessing]] = "-", Table1[[#This Row],[Data partitioning]] = "-", Table1[[#This Row],[Partitions disjoint level]] = "-", Table1[[#This Row],[Model description]] ="-", Table1[[#This Row],[Training details]] = "-", Table1[[#This Row],[Final model selection]] = "-", Table1[[#This Row],[Discarded after full-text review]])),"")
A70: Proceedings of the 2022 International Conference on Multimodal Interaction | C70: ACM | E70: TRUE | L70: =IF(OR(Table1[[#This Row],[Does not regard DAIC-WOZ]]=TRUE,Table1[[#This Row],[Does not use MAE]]=TRUE,Table1[[#This Row],[Does not introduce new model]]=TRUE,Table1[[#This Row],[Not in English]]=TRUE,Table1[[#This Row],[Not retrieved]]=TRUE),TRUE,FALSE) -> FALSE | AF70: =IF(NOT(Table1[[#This Row],[Data modality]] = ""), NOT(OR(Table1[[#This Row],[Data preprocessing]] = "-", Table1[[#This Row],[Data partitioning]] = "-", Table1[[#This Row],[Partitions disjoint level]] = "-", Table1[[#This Row],[Model description]] ="-", Table1[[#This Row],[Training details]] = "-", Table1[[#This Row],[Final model selection]] = "-", Table1[[#This Row],[Discarded after full-text review]])),"")
A71: Proceedings of the 1st International Workshop on Advances in Environmental Sensing Systems for Smart Cities | C71: ACM | E71: TRUE | L71: =IF(OR(Table1[[#This Row],[Does not regard DAIC-WOZ]]=TRUE,Table1[[#This Row],[Does not use MAE]]=TRUE,Table1[[#This Row],[Does not introduce new model]]=TRUE,Table1[[#This Row],[Not in English]]=TRUE,Table1[[#This Row],[Not retrieved]]=TRUE),TRUE,FALSE) -> FALSE | AF71: =IF(NOT(Table1[[#This Row],[Data modality]] = ""), NOT(OR(Table1[[#This Row],[Data preprocessing]] = "-", Table1[[#This Row],[Data partitioning]] = "-", Table1[[#This Row],[Partitions disjoint level]] = "-", Table1[[#This Row],[Model description]] ="-", Table1[[#This Row],[Training details]] = "-", Table1[[#This Row],[Final model selection]] = "-", Table1[[#This Row],[Discarded after full-text review]])),"")
A72: Evaluating Acoustic and Linguistic Features of Detecting Depression Sub-Challenge Dataset | B72: https://doi.org/10.1145/3347320.3357693 | C72: ACM | E72: FALSE | F72: AVEC2019 | G72: TRUE | L72: =IF(OR(Table1[[#This Row],[Does not regard DAIC-WOZ]]=TRUE,Table1[[#This Row],[Does not use MAE]]=TRUE,Table1[[#This Row],[Does not introduce new model]]=TRUE,Table1[[#This Row],[Not in English]]=TRUE,Table1[[#This Row],[Not retrieved]]=TRUE),TRUE,FALSE) -> TRUE | AF72: =IF(NOT(Table1[[#This Row],[Data modality]] = ""), NOT(OR(Table1[[#This Row],[Data preprocessing]] = "-", Table1[[#This Row],[Data partitioning]] = "-", Table1[[#This Row],[Partitions disjoint level]] = "-", Table1[[#This Row],[Model description]] ="-", Table1[[#This Row],[Training details]] = "-", Table1[[#This Row],[Final model selection]] = "-", Table1[[#This Row],[Discarded after full-text review]])),"")
A73: Topic Modeling Based Multi-modal Depression Detection | B73: https://doi.org/10.1145/3133944.3133945 | C73: ACM | E73: FALSE | F73: AVEC2017 | G73: TRUE | L73: =IF(OR(Table1[[#This Row],[Does not regard DAIC-WOZ]]=TRUE,Table1[[#This Row],[Does not use MAE]]=TRUE,Table1[[#This Row],[Does not introduce new model]]=TRUE,Table1[[#This Row],[Not in English]]=TRUE,Table1[[#This Row],[Not retrieved]]=TRUE),TRUE,FALSE) -> TRUE | AF73: =IF(NOT(Table1[[#This Row],[Data modality]] = ""), NOT(OR(Table1[[#This Row],[Data preprocessing]] = "-", Table1[[#This Row],[Data partitioning]] = "-", Table1[[#This Row],[Partitions disjoint level]] = "-", Table1[[#This Row],[Model description]] ="-", Table1[[#This Row],[Training details]] = "-", Table1[[#This Row],[Final model selection]] = "-", Table1[[#This Row],[Discarded after full-text review]])),"")
A74: AVEC 2017: Real-life Depression, and Affect Recognition Workshop and Challenge | B74: https://doi.org/10.1145/3133944.3133953 | C74: ACM | E74: TRUE | L74: =IF(OR(Table1[[#This Row],[Does not regard DAIC-WOZ]]=TRUE,Table1[[#This Row],[Does not use MAE]]=TRUE,Table1[[#This Row],[Does not introduce new model]]=TRUE,Table1[[#This Row],[Not in English]]=TRUE,Table1[[#This Row],[Not retrieved]]=TRUE),TRUE,FALSE) -> FALSE | AF74: =IF(NOT(Table1[[#This Row],[Data modality]] = ""), NOT(OR(Table1[[#This Row],[Data preprocessing]] = "-", Table1[[#This Row],[Data partitioning]] = "-", Table1[[#This Row],[Partitions disjoint level]] = "-", Table1[[#This Row],[Model description]] ="-", Table1[[#This Row],[Training details]] = "-", Table1[[#This Row],[Final model selection]] = "-", Table1[[#This Row],[Discarded after full-text review]])),"")
A75: Proceedings of the 2023 Fifteenth International Conference on Contemporary Computing | C75: ACM | E75: TRUE | L75: =IF(OR(Table1[[#This Row],[Does not regard DAIC-WOZ]]=TRUE,Table1[[#This Row],[Does not use MAE]]=TRUE,Table1[[#This Row],[Does not introduce new model]]=TRUE,Table1[[#This Row],[Not in English]]=TRUE,Table1[[#This Row],[Not retrieved]]=TRUE),TRUE,FALSE) -> FALSE | AF75: =IF(NOT(Table1[[#This Row],[Data modality]] = ""), NOT(OR(Table1[[#This Row],[Data preprocessing]] = "-", Table1[[#This Row],[Data partitioning]] = "-", Table1[[#This Row],[Partitions disjoint level]] = "-", Table1[[#This Row],[Model description]] ="-", Table1[[#This Row],[Training details]] = "-", Table1[[#This Row],[Final model selection]] = "-", Table1[[#This Row],[Discarded after full-text review]])),"")
A76: Proceedings of the 2022 5th Artificial Intelligence and Cloud Computing Conference | C76: ACM | E76: TRUE | L76: =IF(OR(Table1[[#This Row],[Does not regard DAIC-WOZ]]=TRUE,Table1[[#This Row],[Does not use MAE]]=TRUE,Table1[[#This Row],[Does not introduce new model]]=TRUE,Table1[[#This Row],[Not in English]]=TRUE,Table1[[#This Row],[Not retrieved]]=TRUE),TRUE,FALSE) -> FALSE | AF76: =IF(NOT(Table1[[#This Row],[Data modality]] = ""), NOT(OR(Table1[[#This Row],[Data preprocessing]] = "-", Table1[[#This Row],[Data partitioning]] = "-", Table1[[#This Row],[Partitions disjoint level]] = "-", Table1[[#This Row],[Model description]] ="-", Table1[[#This Row],[Training details]] = "-", Table1[[#This Row],[Final model selection]] = "-", Table1[[#This Row],[Discarded after full-text review]])),"")
A77: Companion of the 2024 on ACM International Joint Conference on Pervasive and Ubiquitous Computing | C77: ACM | E77: TRUE | L77: =IF(OR(Table1[[#This Row],[Does not regard DAIC-WOZ]]=TRUE,Table1[[#This Row],[Does not use MAE]]=TRUE,Table1[[#This Row],[Does not introduce new model]]=TRUE,Table1[[#This Row],[Not in English]]=TRUE,Table1[[#This Row],[Not retrieved]]=TRUE),TRUE,FALSE) -> FALSE | AF77: =IF(NOT(Table1[[#This Row],[Data modality]] = ""), NOT(OR(Table1[[#This Row],[Data preprocessing]] = "-", Table1[[#This Row],[Data partitioning]] = "-", Table1[[#This Row],[Partitions disjoint level]] = "-", Table1[[#This Row],[Model description]] ="-", Table1[[#This Row],[Training details]] = "-", Table1[[#This Row],[Final model selection]] = "-", Table1[[#This Row],[Discarded after full-text review]])),"")
A78: Adjunct Proceedings of the 32nd ACM Conference on User Modeling, Adaptation and Personalization | C78: ACM | E78: TRUE | L78: =IF(OR(Table1[[#This Row],[Does not regard DAIC-WOZ]]=TRUE,Table1[[#This Row],[Does not use MAE]]=TRUE,Table1[[#This Row],[Does not introduce new model]]=TRUE,Table1[[#This Row],[Not in English]]=TRUE,Table1[[#This Row],[Not retrieved]]=TRUE),TRUE,FALSE) -> FALSE | AF78: =IF(NOT(Table1[[#This Row],[Data modality]] = ""), NOT(OR(Table1[[#This Row],[Data preprocessing]] = "-", Table1[[#This Row],[Data partitioning]] = "-", Table1[[#This Row],[Partitions disjoint level]] = "-", Table1[[#This Row],[Model description]] ="-", Table1[[#This Row],[Training details]] = "-", Table1[[#This Row],[Final model selection]] = "-", Table1[[#This Row],[Discarded after full-text review]])),"")
A79: Reaching Out: Investigating Different Modalities to Help People with Visual Impairments Acquire Items | B79: https://doi.org/10.1145/3132525.3134817 | C79: ACM | E79: TRUE | L79: =IF(OR(Table1[[#This Row],[Does not regard DAIC-WOZ]]=TRUE,Table1[[#This Row],[Does not use MAE]]=TRUE,Table1[[#This Row],[Does not introduce new model]]=TRUE,Table1[[#This Row],[Not in English]]=TRUE,Table1[[#This Row],[Not retrieved]]=TRUE),TRUE,FALSE) -> FALSE | AF79: =IF(NOT(Table1[[#This Row],[Data modality]] = ""), NOT(OR(Table1[[#This Row],[Data preprocessing]] = "-", Table1[[#This Row],[Data partitioning]] = "-", Table1[[#This Row],[Partitions disjoint level]] = "-", Table1[[#This Row],[Model description]] ="-", Table1[[#This Row],[Training details]] = "-", Table1[[#This Row],[Final model selection]] = "-", Table1[[#This Row],[Discarded after full-text review]])),"")
A80: Companion Publication of the 2022 International Conference on Multimodal Interaction | C80: ACM | E80: TRUE | L80: =IF(OR(Table1[[#This Row],[Does not regard DAIC-WOZ]]=TRUE,Table1[[#This Row],[Does not use MAE]]=TRUE,Table1[[#This Row],[Does not introduce new model]]=TRUE,Table1[[#This Row],[Not in English]]=TRUE,Table1[[#This Row],[Not retrieved]]=TRUE),TRUE,FALSE) -> FALSE | AF80: =IF(NOT(Table1[[#This Row],[Data modality]] = ""), NOT(OR(Table1[[#This Row],[Data preprocessing]] = "-", Table1[[#This Row],[Data partitioning]] = "-", Table1[[#This Row],[Partitions disjoint level]] = "-", Table1[[#This Row],[Model description]] ="-", Table1[[#This Row],[Training details]] = "-", Table1[[#This Row],[Final model selection]] = "-", Table1[[#This Row],[Discarded after full-text review]])),"")
A81: AVEC 2016: Depression, Mood, and Emotion Recognition Workshop and Challenge | B81: https://doi.org/10.1145/2988257.2988258 | C81: ACM | E81: TRUE | L81: =IF(OR(Table1[[#This Row],[Does not regard DAIC-WOZ]]=TRUE,Table1[[#This Row],[Does not use MAE]]=TRUE,Table1[[#This Row],[Does not introduce new model]]=TRUE,Table1[[#This Row],[Not in English]]=TRUE,Table1[[#This Row],[Not retrieved]]=TRUE),TRUE,FALSE) -> FALSE | AF81: =IF(NOT(Table1[[#This Row],[Data modality]] = ""), NOT(OR(Table1[[#This Row],[Data preprocessing]] = "-", Table1[[#This Row],[Data partitioning]] = "-", Table1[[#This Row],[Partitions disjoint level]] = "-", Table1[[#This Row],[Model description]] ="-", Table1[[#This Row],[Training details]] = "-", Table1[[#This Row],[Final model selection]] = "-", Table1[[#This Row],[Discarded after full-text review]])),"")
A82: Proceedings of the 2024 7th International Conference on Machine Learning and Machine Intelligence (MLMI) | C82: ACM | E82: TRUE | L82: =IF(OR(Table1[[#This Row],[Does not regard DAIC-WOZ]]=TRUE,Table1[[#This Row],[Does not use MAE]]=TRUE,Table1[[#This Row],[Does not introduce new model]]=TRUE,Table1[[#This Row],[Not in English]]=TRUE,Table1[[#This Row],[Not retrieved]]=TRUE),TRUE,FALSE) -> FALSE | AF82: =IF(NOT(Table1[[#This Row],[Data modality]] = ""), NOT(OR(Table1[[#This Row],[Data preprocessing]] = "-", Table1[[#This Row],[Data partitioning]] = "-", Table1[[#This Row],[Partitions disjoint level]] = "-", Table1[[#This Row],[Model description]] ="-", Table1[[#This Row],[Training details]] = "-", Table1[[#This Row],[Final model selection]] = "-", Table1[[#This Row],[Discarded after full-text review]])),"")
A83: Proceedings of Mensch und Computer 2023 | C83: ACM | E83: TRUE | L83: =IF(OR(Table1[[#This Row],[Does not regard DAIC-WOZ]]=TRUE,Table1[[#This Row],[Does not use MAE]]=TRUE,Table1[[#This Row],[Does not introduce new model]]=TRUE,Table1[[#This Row],[Not in English]]=TRUE,Table1[[#This Row],[Not retrieved]]=TRUE),TRUE,FALSE) -> FALSE | AF83: =IF(NOT(Table1[[#This Row],[Data modality]] = ""), NOT(OR(Table1[[#This Row],[Data preprocessing]] = "-", Table1[[#This Row],[Data partitioning]] = "-", Table1[[#This Row],[Partitions disjoint level]] = "-", Table1[[#This Row],[Model description]] ="-", Table1[[#This Row],[Training details]] = "-", Table1[[#This Row],[Final model selection]] = "-", Table1[[#This Row],[Discarded after full-text review]])),"")
A84: Proceedings of the 2024 Conference on Human Information Interaction and Retrieval | C84: ACM | E84: TRUE | L84: =IF(OR(Table1[[#This Row],[Does not regard DAIC-WOZ]]=TRUE,Table1[[#This Row],[Does not use MAE]]=TRUE,Table1[[#This Row],[Does not introduce new model]]=TRUE,Table1[[#This Row],[Not in English]]=TRUE,Table1[[#This Row],[Not retrieved]]=TRUE),TRUE,FALSE) -> FALSE | AF84: =IF(NOT(Table1[[#This Row],[Data modality]] = ""), NOT(OR(Table1[[#This Row],[Data preprocessing]] = "-", Table1[[#This Row],[Data partitioning]] = "-", Table1[[#This Row],[Partitions disjoint level]] = "-", Table1[[#This Row],[Model description]] ="-", Table1[[#This Row],[Training details]] = "-", Table1[[#This Row],[Final model selection]] = "-", Table1[[#This Row],[Discarded after full-text review]])),"")
A85: Machine Learning in Mental Health: A Systematic Review of the HCI Literature to Support the Development of Effective and Implementable ML Systems | B85: https://doi.org/10.1145/3398069 | C85: ACM | E85: TRUE | L85: =IF(OR(Table1[[#This Row],[Does not regard DAIC-WOZ]]=TRUE,Table1[[#This Row],[Does not use MAE]]=TRUE,Table1[[#This Row],[Does not introduce new model]]=TRUE,Table1[[#This Row],[Not in English]]=TRUE,Table1[[#This Row],[Not retrieved]]=TRUE),TRUE,FALSE) -> FALSE | AF85: =IF(NOT(Table1[[#This Row],[Data modality]] = ""), NOT(OR(Table1[[#This Row],[Data preprocessing]] = "-", Table1[[#This Row],[Data partitioning]] = "-", Table1[[#This Row],[Partitions disjoint level]] = "-", Table1[[#This Row],[Model description]] ="-", Table1[[#This Row],[Training details]] = "-", Table1[[#This Row],[Final model selection]] = "-", Table1[[#This Row],[Discarded after full-text review]])),"")
A86: Companion Publication of the 25th International Conference on Multimodal Interaction | C86: ACM | E86: TRUE | L86: =IF(OR(Table1[[#This Row],[Does not regard DAIC-WOZ]]=TRUE,Table1[[#This Row],[Does not use MAE]]=TRUE,Table1[[#This Row],[Does not introduce new model]]=TRUE,Table1[[#This Row],[Not in English]]=TRUE,Table1[[#This Row],[Not retrieved]]=TRUE),TRUE,FALSE) -> FALSE | AF86: =IF(NOT(Table1[[#This Row],[Data modality]] = ""), NOT(OR(Table1[[#This Row],[Data preprocessing]] = "-", Table1[[#This Row],[Data partitioning]] = "-", Table1[[#This Row],[Partitions disjoint level]] = "-", Table1[[#This Row],[Model description]] ="-", Table1[[#This Row],[Training details]] = "-", Table1[[#This Row],[Final model selection]] = "-", Table1[[#This Row],[Discarded after full-text review]])),"")
A87: Proceedings of the 25th International Conference on Multimodal Interaction | C87: ACM | E87: TRUE | L87: =IF(OR(Table1[[#This Row],[Does not regard DAIC-WOZ]]=TRUE,Table1[[#This Row],[Does not use MAE]]=TRUE,Table1[[#This Row],[Does not introduce new model]]=TRUE,Table1[[#This Row],[Not in English]]=TRUE,Table1[[#This Row],[Not retrieved]]=TRUE),TRUE,FALSE) -> FALSE | AF87: =IF(NOT(Table1[[#This Row],[Data modality]] = ""), NOT(OR(Table1[[#This Row],[Data preprocessing]] = "-", Table1[[#This Row],[Data partitioning]] = "-", Table1[[#This Row],[Partitions disjoint level]] = "-", Table1[[#This Row],[Model description]] ="-", Table1[[#This Row],[Training details]] = "-", Table1[[#This Row],[Final model selection]] = "-", Table1[[#This Row],[Discarded after full-text review]])),"")
A88: Proceedings of the 29th International Conference on Intelligent User Interfaces | C88: ACM | E88: TRUE | L88: =IF(OR(Table1[[#This Row],[Does not regard DAIC-WOZ]]=TRUE,Table1[[#This Row],[Does not use MAE]]=TRUE,Table1[[#This Row],[Does not introduce new model]]=TRUE,Table1[[#This Row],[Not in English]]=TRUE,Table1[[#This Row],[Not retrieved]]=TRUE),TRUE,FALSE) -> FALSE | AF88: =IF(NOT(Table1[[#This Row],[Data modality]] = ""), NOT(OR(Table1[[#This Row],[Data preprocessing]] = "-", Table1[[#This Row],[Data partitioning]] = "-", Table1[[#This Row],[Partitions disjoint level]] = "-", Table1[[#This Row],[Model description]] ="-", Table1[[#This Row],[Training details]] = "-", Table1[[#This Row],[Final model selection]] = "-", Table1[[#This Row],[Discarded after full-text review]])),"")
A89: Proceedings of the 37th Annual ACM Symposium on User Interface Software and Technology | C89: ACM | E89: TRUE | L89: =IF(OR(Table1[[#This Row],[Does not regard DAIC-WOZ]]=TRUE,Table1[[#This Row],[Does not use MAE]]=TRUE,Table1[[#This Row],[Does not introduce new model]]=TRUE,Table1[[#This Row],[Not in English]]=TRUE,Table1[[#This Row],[Not retrieved]]=TRUE),TRUE,FALSE) -> FALSE | AF89: =IF(NOT(Table1[[#This Row],[Data modality]] = ""), NOT(OR(Table1[[#This Row],[Data preprocessing]] = "-", Table1[[#This Row],[Data partitioning]] = "-", Table1[[#This Row],[Partitions disjoint level]] = "-", Table1[[#This Row],[Model description]] ="-", Table1[[#This Row],[Training details]] = "-", Table1[[#This Row],[Final model selection]] = "-", Table1[[#This Row],[Discarded after full-text review]])),"")
A90: Proceedings of the 4th Conference on Conversational User Interfaces | C90: ACM | E90: TRUE | L90: =IF(OR(Table1[[#This Row],[Does not regard DAIC-WOZ]]=TRUE,Table1[[#This Row],[Does not use MAE]]=TRUE,Table1[[#This Row],[Does not introduce new model]]=TRUE,Table1[[#This Row],[Not in English]]=TRUE,Table1[[#This Row],[Not retrieved]]=TRUE),TRUE,FALSE) -> FALSE | AF90: =IF(NOT(Table1[[#This Row],[Data modality]] = ""), NOT(OR(Table1[[#This Row],[Data preprocessing]] = "-", Table1[[#This Row],[Data partitioning]] = "-", Table1[[#This Row],[Partitions disjoint level]] = "-", Table1[[#This Row],[Model description]] ="-", Table1[[#This Row],[Training details]] = "-", Table1[[#This Row],[Final model selection]] = "-", Table1[[#This Row],[Discarded after full-text review]])),"")
A91: Extended Abstracts of the CHI Conference on Human Factors in Computing Systems | C91: ACM | E91: TRUE | L91: =IF(OR(Table1[[#This Row],[Does not regard DAIC-WOZ]]=TRUE,Table1[[#This Row],[Does not use MAE]]=TRUE,Table1[[#This Row],[Does not introduce new model]]=TRUE,Table1[[#This Row],[Not in English]]=TRUE,Table1[[#This Row],[Not retrieved]]=TRUE),TRUE,FALSE) -> FALSE | AF91: =IF(NOT(Table1[[#This Row],[Data modality]] = ""), NOT(OR(Table1[[#This Row],[Data preprocessing]] = "-", Table1[[#This Row],[Data partitioning]] = "-", Table1[[#This Row],[Partitions disjoint level]] = "-", Table1[[#This Row],[Model description]] ="-", Table1[[#This Row],[Training details]] = "-", Table1[[#This Row],[Final model selection]] = "-", Table1[[#This Row],[Discarded after full-text review]])),"")
A92: The Development and Validation of the Technology-Supported Reflection Inventory | B92: https://doi.org/10.1145/3411764.3445673 | C92: ACM | E92: TRUE | L92: =IF(OR(Table1[[#This Row],[Does not regard DAIC-WOZ]]=TRUE,Table1[[#This Row],[Does not use MAE]]=TRUE,Table1[[#This Row],[Does not introduce new model]]=TRUE,Table1[[#This Row],[Not in English]]=TRUE,Table1[[#This Row],[Not retrieved]]=TRUE),TRUE,FALSE) -> FALSE | AF92: =IF(NOT(Table1[[#This Row],[Data modality]] = ""), NOT(OR(Table1[[#This Row],[Data preprocessing]] = "-", Table1[[#This Row],[Data partitioning]] = "-", Table1[[#This Row],[Partitions disjoint level]] = "-", Table1[[#This Row],[Model description]] ="-", Table1[[#This Row],[Training details]] = "-", Table1[[#This Row],[Final model selection]] = "-", Table1[[#This Row],[Discarded after full-text review]])),"")
A93: Proceedings of the 2024 10th International Conference on Computing and Artificial Intelligence | C93: ACM | E93: TRUE | L93: =IF(OR(Table1[[#This Row],[Does not regard DAIC-WOZ]]=TRUE,Table1[[#This Row],[Does not use MAE]]=TRUE,Table1[[#This Row],[Does not introduce new model]]=TRUE,Table1[[#This Row],[Not in English]]=TRUE,Table1[[#This Row],[Not retrieved]]=TRUE),TRUE,FALSE) -> FALSE | AF93: =IF(NOT(Table1[[#This Row],[Data modality]] = ""), NOT(OR(Table1[[#This Row],[Data preprocessing]] = "-", Table1[[#This Row],[Data partitioning]] = "-", Table1[[#This Row],[Partitions disjoint level]] = "-", Table1[[#This Row],[Model description]] ="-", Table1[[#This Row],[Training details]] = "-", Table1[[#This Row],[Final model selection]] = "-", Table1[[#This Row],[Discarded after full-text review]])),"")
A94: Gender Bias in Word Embeddings: A Comprehensive Analysis of Frequency, Syntax, and Semantics | B94: https://doi.org/10.1145/3514094.3534162 | C94: ACM | E94: TRUE | L94: =IF(OR(Table1[[#This Row],[Does not regard DAIC-WOZ]]=TRUE,Table1[[#This Row],[Does not use MAE]]=TRUE,Table1[[#This Row],[Does not introduce new model]]=TRUE,Table1[[#This Row],[Not in English]]=TRUE,Table1[[#This Row],[Not retrieved]]=TRUE),TRUE,FALSE) -> FALSE | AF94: =IF(NOT(Table1[[#This Row],[Data modality]] = ""), NOT(OR(Table1[[#This Row],[Data preprocessing]] = "-", Table1[[#This Row],[Data partitioning]] = "-", Table1[[#This Row],[Partitions disjoint level]] = "-", Table1[[#This Row],[Model description]] ="-", Table1[[#This Row],[Training details]] = "-", Table1[[#This Row],[Final model selection]] = "-", Table1[[#This Row],[Discarded after full-text review]])),"")
A95: Proceedings of the 2022 4th International Conference on Robotics, Intelligent Control and Artificial Intelligence | C95: ACM | E95: TRUE | L95: =IF(OR(Table1[[#This Row],[Does not regard DAIC-WOZ]]=TRUE,Table1[[#This Row],[Does not use MAE]]=TRUE,Table1[[#This Row],[Does not introduce new model]]=TRUE,Table1[[#This Row],[Not in English]]=TRUE,Table1[[#This Row],[Not retrieved]]=TRUE),TRUE,FALSE) -> FALSE | AF95: =IF(NOT(Table1[[#This Row],[Data modality]] = ""), NOT(OR(Table1[[#This Row],[Data preprocessing]] = "-", Table1[[#This Row],[Data partitioning]] = "-", Table1[[#This Row],[Partitions disjoint level]] = "-", Table1[[#This Row],[Model description]] ="-", Table1[[#This Row],[Training details]] = "-", Table1[[#This Row],[Final model selection]] = "-", Table1[[#This Row],[Discarded after full-text review]])),"")
A96: Proceedings of the 2023 CHI Conference on Human Factors in Computing Systems | C96: ACM | E96: TRUE | L96: =IF(OR(Table1[[#This Row],[Does not regard DAIC-WOZ]]=TRUE,Table1[[#This Row],[Does not use MAE]]=TRUE,Table1[[#This Row],[Does not introduce new model]]=TRUE,Table1[[#This Row],[Not in English]]=TRUE,Table1[[#This Row],[Not retrieved]]=TRUE),TRUE,FALSE) -> FALSE | AF96: =IF(NOT(Table1[[#This Row],[Data modality]] = ""), NOT(OR(Table1[[#This Row],[Data preprocessing]] = "-", Table1[[#This Row],[Data partitioning]] = "-", Table1[[#This Row],[Partitions disjoint level]] = "-", Table1[[#This Row],[Model description]] ="-", Table1[[#This Row],[Training details]] = "-", Table1[[#This Row],[Final model selection]] = "-", Table1[[#This Row],[Discarded after full-text review]])),"")
A97: Proceedings of the 2024 13th International Conference on Computing and Pattern Recognition | C97: ACM | E97: TRUE | L97: =IF(OR(Table1[[#This Row],[Does not regard DAIC-WOZ]]=TRUE,Table1[[#This Row],[Does not use MAE]]=TRUE,Table1[[#This Row],[Does not introduce new model]]=TRUE,Table1[[#This Row],[Not in English]]=TRUE,Table1[[#This Row],[Not retrieved]]=TRUE),TRUE,FALSE) -> FALSE | AF97: =IF(NOT(Table1[[#This Row],[Data modality]] = ""), NOT(OR(Table1[[#This Row],[Data preprocessing]] = "-", Table1[[#This Row],[Data partitioning]] = "-", Table1[[#This Row],[Partitions disjoint level]] = "-", Table1[[#This Row],[Model description]] ="-", Table1[[#This Row],[Training details]] = "-", Table1[[#This Row],[Final model selection]] = "-", Table1[[#This Row],[Discarded after full-text review]])),"")
A98: Multimodal and Multiresolution Depression Detection from Speech and Facial Landmark Features | B98: https://doi.org/10.1145/2988257.2988261 | C98: ACM | E98: TRUE | L98: =IF(OR(Table1[[#This Row],[Does not regard DAIC-WOZ]]=TRUE,Table1[[#This Row],[Does not use MAE]]=TRUE,Table1[[#This Row],[Does not introduce new model]]=TRUE,Table1[[#This Row],[Not in English]]=TRUE,Table1[[#This Row],[Not retrieved]]=TRUE),TRUE,FALSE) -> FALSE | AF98: =IF(NOT(Table1[[#This Row],[Data modality]] = ""), NOT(OR(Table1[[#This Row],[Data preprocessing]] = "-", Table1[[#This Row],[Data partitioning]] = "-", Table1[[#This Row],[Partitions disjoint level]] = "-", Table1[[#This Row],[Model description]] ="-", Table1[[#This Row],[Training details]] = "-", Table1[[#This Row],[Final model selection]] = "-", Table1[[#This Row],[Discarded after full-text review]])),"")
A99: Companion Proceedings of the 2024 Annual Symposium on Computer-Human Interaction in Play | C99: ACM | E99: TRUE | L99: =IF(OR(Table1[[#This Row],[Does not regard DAIC-WOZ]]=TRUE,Table1[[#This Row],[Does not use MAE]]=TRUE,Table1[[#This Row],[Does not introduce new model]]=TRUE,Table1[[#This Row],[Not in English]]=TRUE,Table1[[#This Row],[Not retrieved]]=TRUE),TRUE,FALSE) -> FALSE | AF99: =IF(NOT(Table1[[#This Row],[Data modality]] = ""), NOT(OR(Table1[[#This Row],[Data preprocessing]] = "-", Table1[[#This Row],[Data partitioning]] = "-", Table1[[#This Row],[Partitions disjoint level]] = "-", Table1[[#This Row],[Model description]] ="-", Table1[[#This Row],[Training details]] = "-", Table1[[#This Row],[Final model selection]] = "-", Table1[[#This Row],[Discarded after full-text review]])),"")
A100: Proceedings of the 20th Brazilian Symposium on Information Systems | C100: ACM | E100: TRUE | L100: =IF(OR(Table1[[#This Row],[Does not regard DAIC-WOZ]]=TRUE,Table1[[#This Row],[Does not use MAE]]=TRUE,Table1[[#This Row],[Does not introduce new model]]=TRUE,Table1[[#This Row],[Not in English]]=TRUE,Table1[[#This Row],[Not retrieved]]=TRUE),TRUE,FALSE) -> FALSE | AF100: =IF(NOT(Table1[[#This Row],[Data modality]] = ""), NOT(OR(Table1[[#This Row],[Data preprocessing]] = "-", Table1[[#This Row],[Data partitioning]] = "-", Table1[[#This Row],[Partitions disjoint level]] = "-", Table1[[#This Row],[Model description]] ="-", Table1[[#This Row],[Training details]] = "-", Table1[[#This Row],[Final model selection]] = "-", Table1[[#This Row],[Discarded after full-text review]])),"")
...

Sheet Daily plan
B2: date | C2: 45747 | D2: 45748 | E2: 45749 | F2: 45750 | G2: 45751 | H2: 45752 | I2: 45753 | J2: 45754 | K2: 45755 | L2: 45756 | M2: 45757 | N2: 45758 | O2: 45759 | P2: 45760
B3: avg volume required | C3: =(Stats!$E$6)/($P$2-C2-1) -> 0 | D3: =(Stats!$E$6)/($P$2-D2) -> 0 | E3: =(Stats!$E$6)/($P$2-E2) -> 0 | F3: =(Stats!$E$6)/($P$2-F2) -> 0 | G3: =(Stats!$E$6)/($P$2-G2) -> 0 | H3: =(Stats!$E$6)/($P$2-H2) -> 0 | I3: =(Stats!$E$6)/($P$2-I2) -> 0 | J3: =(Stats!$E$6)/($P$2-J2) -> 0 | K3: =(Stats!$E$6)/($P$2-K2) -> 0 | ... O3: =(Stats!$E$6)/($P$2-O2) -> 0

Sheet Stats
C1: Screening
C2: Article and abstract | D2: Full-text | E2: Quality screening
B3: Pool | C3: =C4+C5+C6 -> 345 | D3: =C4 -> 108 | E3: =D4 -> 56
B4: Accepted | C4: =COUNTIF(Table1[Irrelevant title/abstract], FALSE) -> 108 | D4: =D3-D5-D7 -> 56 | E4: =COUNTIF(Screening!AF2:AF339, TRUE) -> 5 | F4: =E4/E3 -> 0.089285714
B5: Discarded | C5: =COUNTIF(Table1[Irrelevant title/abstract], TRUE) -> 237 | D5: =COUNTIF(Table1[Discarded after full-text review], TRUE) - D7 -> 50 | E5: =COUNTIF(Screening!AF2:AF339, FALSE) -> 51 | F5: =E5/E3 -> 0.91071429
B6: Remaining | C6: =COUNTIF(Table1[Irrelevant title/abstract], "") -> 0 | D6: =D3-D4-D5-D7 -> 0 | E6: =E3-E4-E5 -> 0 | F6: =E6/E3 -> 0
B7: Not retrieved | C7: N/A | D7: =COUNTIF(Table1[Not retrieved], TRUE) -> 2 | E7: N/A
